Workbook

Sheet Option_Portfolio
B3: # contracts | C3: option | D3: underlying | E3: K | F3: T (in years) | G3: σ (annual) | H3: risk free rate
B4: 7000 | C4: long put | D4: NESN | E4: 85 | F4: 0.5 | G4: 0.17 | H4: 0.01
B5: 2000 | C5: short call | D5: SREN | E5: 120 | F5: 0.5 | G5: 0.22 | H5: 0.01

Sheet Underlying_Assets
C2: Beta
B3: NSEN | C3: 0.75
B4: SREN | C4: 1.1
A7: date | C7: NSEN | D7: SREN | E7: P_SMI | F7: SMI | G7: CHF/USD | H7: R_NSEN | I7: R_SREN | J7: R_SMI | K7: R_CHF/USD
A8: 45232 | C8: 100.52 | D8: 100.4 | E8: 10591.979 | F8: 0.0083865592 | G8: 1.1034483 | H8: 0 | I8: 0 | J8: 0 | K8: 0
A9: 45233 | C9: 99.75 | D9: 99.26 | E9: 10579.672 | F9: -0.0011619935 | G9: 1.1131519 | H9: =(C9/C8)-1 -> -0.0076601671 | I9: =(D9/D8)-1 -> -0.011354582 | J9: =(E9/E8)-1 -> -0.0011619935 | K9: =(G9/G8)-1 -> 0.0087938873
A10: 45236 | C10: 99.87 | D10: 99.1 | E10: 10576.754 | F10: -0.00027577402 | G10: 1.1146408 | H10: =(C10/C9)-1 -> 0.0012030075 | I10: =(D10/D9)-1 -> -0.0016119283 | J10: =(E10/E9)-1 -> -0.00027577402 | K10: =(G10/G9)-1 -> 0.0013375533
A11: 45237 | C11: 99.62 | D11: 98.84 | E11: 10571.033 | F11: -0.00054094184 | G11: 1.1106793 | H11: =(C11/C10)-1 -> -0.0025032542 | I11: =(D11/D10)-1 -> -0.0026236125 | J11: =(E11/E10)-1 -> -0.00054094184 | K11: =(G11/G10)-1 -> -0.0035540597
A12: 45238 | C12: 99.07 | D12: 98.7 | E12: 10595.061 | F12: 0.0022730268 | G12: 1.1129661 | H12: =(C12/C11)-1 -> -0.0055209797 | I12: =(D12/D11)-1 -> -0.0014164306 | J12: =(E12/E11)-1 -> 0.0022730268 | K12: =(G12/G11)-1 -> 0.0020589202
A13: 45239 | C13: 99.91 | D13: 98.36 | E13: 10644.99 | F13: 0.0047124541 | G13: 1.1119142 | H13: =(C13/C12)-1 -> 0.0084788533 | I13: =(D13/D12)-1 -> -0.0034447822 | J13: =(E13/E12)-1 -> 0.0047124541 | K13: =(G13/G12)-1 -> -0.00094513211
A14: 45240 | C14: 99.38 | D14: 97.96 | E14: 10555.353 | F14: -0.0084204991 | G14: 1.1073583 | H14: =(C14/C13)-1 -> -0.0053047743 | I14: =(D14/D13)-1 -> -0.0040666938 | J14: =(E14/E13)-1 -> -0.0084204991 | K14: =(G14/G13)-1 -> -0.0040973485
A15: 45243 | C15: 98.9 | D15: 99.2 | E15: 10590.393 | F15: 0.0033195704 | G15: 1.1080946 | H15: =(C15/C14)-1 -> -0.0048299457 | I15: =(D15/D14)-1 -> 0.012658228 | J15: =(E15/E14)-1 -> 0.0033195704 | K15: =(G15/G14)-1 -> 0.00066491577
A16: 45244 | C16: 99.4 | D16: 99.1 | E16: 10715.73 | F16: 0.011835031 | G16: 1.1208878 | H16: =(C16/C15)-1 -> 0.0050556117 | I16: =(D16/D15)-1 -> -0.0010080645 | J16: =(E16/E15)-1 -> 0.011835031 | K16: =(G16/G15)-1 -> 0.011545224
A17: 45245 | C17: 99.6 | D17: 99.14 | E17: 10708.195 | F17: -0.00070323644 | G17: 1.1284134 | H17: =(C17/C16)-1 -> 0.0020120724 | I17: =(D17/D16)-1 -> 0.00040363269 | J17: =(E17/E16)-1 -> -0.00070323644 | K17: =(G17/G16)-1 -> 0.0067139637
A18: 45246 | C18: 98.63 | D18: 99.06 | E18: 10643.069 | F18: -0.0060818873 | G18: 1.126824 | H18: =(C18/C17)-1 -> -0.0097389558 | I18: =(D18/D17)-1 -> -0.00080693968 | J18: =(E18/E17)-1 -> -0.0060818873 | K18: =(G18/G17)-1 -> -0.0014085263
A19: 45247 | C19: 98.99 | D19: 99.98 | E19: 10737.367 | F19: 0.0088601213 | G19: 1.1280316 | H19: =(C19/C18)-1 -> 0.0036500051 | I19: =(D19/D18)-1 -> 0.0092873006 | J19: =(E19/E18)-1 -> 0.0088601213 | K19: =(G19/G18)-1 -> 0.0010716847
A20: 45250 | C20: 98.29 | D20: 100.95 | E20: 10740.269 | F20: 0.00027018316 | G20: 1.1309019 | H20: =(C20/C19)-1 -> -0.0070714214 | I20: =(D20/D19)-1 -> 0.0097019404 | J20: =(E20/E19)-1 -> 0.00027018316 | K20: =(G20/G19)-1 -> 0.0025445209
... A365: 45772 | C365: 85.74 | D365: 144.8 | E365: 11942.049 | F365: 0.00020526309 | G365: 1.1347518 | H365: =(C365/C364)-1 -> -0.019441903 | I365: =(D365/D364)-1 -> 0.00034542314 | J365: =(E365/E364)-1 -> 0.0020526309 | K365: =(G365/G364)-1 -> 0.0048226986

Sheet FI_Portfolio
B3: # bonds | C3: maturity in years | D3: annual coupon
B4: 2000000 | C4: 1 | D4: zero | E4: 0
B5: -1500000 | C5: 3 | D5: 5 | E5: 5
B6: 4000000 | C6: 5 | D6: 2 | E6: 2
B9: Notes:
B10: Negative #bonds means you are short

Sheet TSIR
A1: date | B1: 1y | C1: 2y | D1: 3y | E1: 4y | F1: 5y | G1: 1y | H1: 2y | I1: 3y | J1: 4y | K1: 5y | L1: 1y | M1: 2y | N1: 3y | O1: 4y | P1: 5y
A2: 44200 | B2: 0.1 | C2: 0.11 | D2: 0.16 | E2: 0.26005084 | F2: 0.36 | G2: 0 | H2: 0 | I2: 0 | J2: 0 | K2: 0 | L2: =G2/B2 -> 0 | M2: =H2/C2 -> 0 | N2: =I2/D2 -> 0 | O2: =J2/E2 -> 0 | P2: =K2/F2 -> 0 | R2: YIELDS
A3: 44201 | B3: 0.1 | C3: 0.13 | D3: 0.17 | E3: 0.27536133 | F3: 0.38 | G3: =(B3-B2)/100 -> 0 | H3: =(C3-C2)/100 -> 0.0002 | I3: =(D3-D2)/100 -> 0.0001 | J3: =(E3-E2)/100 -> 0.00015310492 | K3: =(F3-F2)/100 -> 0.0002 | L3: =(B3/B2)-1 -> 0 | M3: =(C3/C2)-1 -> 0.18181818 | N3: =(D3/D2)-1 -> 0.0625 | O3: =(E3/E2)-1 -> 0.058874995 | P3: =(F3/F2)-1 -> 0.055555556 | R3: VARIATIONS
A4: 44202 | B4: 0.11 | C4: 0.14 | D4: 0.2 | E4: 0.31523797 | F4: 0.43 | G4: =(B4-B3)/100 -> 0.0001 | H4: =(C4-C3)/100 -> 0.0001 | I4: =(D4-D3)/100 -> 0.0003 | J4: =(E4-E3)/100 -> 0.00039876643 | K4: =(F4-F3)/100 -> 0.0005 | L4: =(B4/B3)-1 -> 0.1 | M4: =(C4/C3)-1 -> 0.076923077 | N4: =(D4/D3)-1 -> 0.17647059 | O4: =(E4/E3)-1 -> 0.1448157 | P4: =(F4/F3)-1 -> 0.13157895 | R4: RETURNS
A5: 44203 | B5: 0.11 | C5: 0.14 | D5: 0.22 | E5: 0.34002364 | F5: 0.46 | G5: =(B5-B4)/100 -> 0 | H5: =(C5-C4)/100 -> 0 | I5: =(D5-D4)/100 -> 0.0002 | J5: =(E5-E4)/100 -> 0.00024785673 | K5: =(F5-F4)/100 -> 0.0003 | L5: =(B5/B4)-1 -> 0 | M5: =(C5/C4)-1 -> 0 | N5: =(D5/D4)-1 -> 0.1 | O5: =(E5/E4)-1 -> 0.078625279 | P5: =(F5/F4)-1 -> 0.069767442
A6: 44204 | B6: 0.1 | C6: 0.14 | D6: 0.24 | E6: 0.36533805 | F6: 0.49 | G6: =(B6-B5)/100 -> -0.0001 | H6: =(C6-C5)/100 -> 0 | I6: =(D6-D5)/100 -> 0.0002 | J6: =(E6-E5)/100 -> 0.00025314409 | K6: =(F6-F5)/100 -> 0.0003 | L6: =(B6/B5)-1 -> -0.090909091 | M6: =(C6/C5)-1 -> 0 | N6: =(D6/D5)-1 -> 0.090909091 | O6: =(E6/E5)-1 -> 0.074448968 | P6: =(F6/F5)-1 -> 0.065217391
A7: 44207 | B7: 0.1 | C7: 0.14 | D7: 0.22 | E7: 0.36043964 | F7: 0.5 | G7: =(B7-B6)/100 -> 0 | H7: =(C7-C6)/100 -> 0 | I7: =(D7-D6)/100 -> -0.0002 | J7: =(E7-E6)/100 -> -4.8984104e-05 | K7: =(F7-F6)/100 -> 0.0001 | L7: =(B7/B6)-1 -> 0 | M7: =(C7/C6)-1 -> 0 | N7: =(D7/D6)-1 -> -0.083333333 | O7: =(E7/E6)-1 -> -0.013407885 | P7: =(F7/F6)-1 -> 0.020408163
A8: 44208 | B8: 0.11 | C8: 0.14 | D8: 0.23 | E8: 0.36541897 | F8: 0.5 | G8: =(B8-B7)/100 -> 0.0001 | H8: =(C8-C7)/100 -> 0 | I8: =(D8-D7)/100 -> 0.0001 | J8: =(E8-E7)/100 -> 4.9793222e-05 | K8: =(F8-F7)/100 -> 0 | L8: =(B8/B7)-1 -> 0.1 | M8: =(C8/C7)-1 -> 0 | N8: =(D8/D7)-1 -> 0.045454545 | O8: =(E8/E7)-1 -> 0.01381458 | P8: =(F8/F7)-1 -> 0
A9: 44209 | B9: 0.12 | C9: 0.14 | D9: 0.22 | E9: 0.35011298 | F9: 0.48 | G9: =(B9-B8)/100 -> 0.0001 | H9: =(C9-C8)/100 -> 0 | I9: =(D9-D8)/100 -> -0.0001 | J9: =(E9-E8)/100 -> -0.0001530599 | K9: =(F9-F8)/100 -> -0.0002 | L9: =(B9/B8)-1 -> 0.090909091 | M9: =(C9/C8)-1 -> 0 | N9: =(D9/D8)-1 -> -0.043478261 | O9: =(E9/E8)-1 -> -0.041886139 | P9: =(F9/F8)-1 -> -0.04
A10: 44210 | B10: 0.1 | C10: 0.16 | D10: 0.23 | E10: 0.36044743 | F10: 0.49 | G10: =(B10-B9)/100 -> -0.0002 | H10: =(C10-C9)/100 -> 0.0002 | I10: =(D10-D9)/100 -> 0.0001 | J10: =(E10-E9)/100 -> 0.00010334455 | K10: =(F10-F9)/100 -> 0.0001 | L10: =(B10/B9)-1 -> -0.16666667 | M10: =(C10/C9)-1 -> 0.14285714 | N10: =(D10/D9)-1 -> 0.045454545 | O10: =(E10/E9)-1 -> 0.029517486 | P10: =(F10/F9)-1 -> 0.020833333
A11: 44211 | B11: 0.1 | C11: 0.13 | D11: 0.2 | E11: 0.33023905 | F11: 0.46 | G11: =(B11-B10)/100 -> 0 | H11: =(C11-C10)/100 -> -0.0003 | I11: =(D11-D10)/100 -> -0.0003 | J11: =(E11-E10)/100 -> -0.00030208377 | K11: =(F11-F10)/100 -> -0.0003 | L11: =(B11/B10)-1 -> 0 | M11: =(C11/C10)-1 -> -0.1875 | N11: =(D11/D10)-1 -> -0.13043478 | O11: =(E11/E10)-1 -> -0.083807997 | P11: =(F11/F10)-1 -> -0.06122449
A12: 44215 | B12: 0.1 | C12: 0.14 | D12: 0.21 | E12: 0.33025798 | F12: 0.45 | G12: =(B12-B11)/100 -> 0 | H12: =(C12-C11)/100 -> 0.0001 | I12: =(D12-D11)/100 -> 0.0001 | J12: =(E12-E11)/100 -> 1.8926313e-07 | K12: =(F12-F11)/100 -> -0.0001 | L12: =(B12/B11)-1 -> 0 | M12: =(C12/C11)-1 -> 0.076923077 | N12: =(D12/D11)-1 -> 0.05 | O12: =(E12/E11)-1 -> 5.7310948e-05 | P12: =(F12/F11)-1 -> -0.02173913
A13: 44216 | B13: 0.1 | C13: 0.13 | D13: 0.19 | E13: 0.32026831 | F13: 0.45 | G13: =(B13-B12)/100 -> 0 | H13: =(C13-C12)/100 -> -0.0001 | I13: =(D13-D12)/100 -> -0.0002 | J13: =(E13-E12)/100 -> -9.9896685e-05 | K13: =(F13-F12)/100 -> 0 | L13: =(B13/B12)-1 -> 0 | M13: =(C13/C12)-1 -> -0.071428571 | N13: =(D13/D12)-1 -> -0.095238095 | O13: =(E13/E12)-1 -> -0.030248076 | P13: =(F13/F12)-1 -> 0
A14: 44217 | B14: 0.1 | C14: 0.13 | D14: 0.19 | E14: 0.32042425 | F14: 0.45 | G14: =(B14-B13)/100 -> 0 | H14: =(C14-C13)/100 -> 0 | I14: =(D14-D13)/100 -> 0 | J14: =(E14-E13)/100 -> 1.5593777e-06 | K14: =(F14-F13)/100 -> 0 | L14: =(B14/B13)-1 -> 0 | M14: =(C14/C13)-1 -> 0 | N14: =(D14/D13)-1 -> 0 | O14: =(E14/E13)-1 -> 0.00048689728 | P14: =(F14/F13)-1 -> 0
A15: 44218 | B15: 0.1 | C15: 0.13 | D15: 0.19 | E15: 0.31548957 | F15: 0.44 | G15: =(B15-B14)/100 -> 0 | H15: =(C15-C14)/100 -> 0 | I15: =(D15-D14)/100 -> 0 | J15: =(E15-E14)/100 -> -4.9346745e-05 | K15: =(F15-F14)/100 -> -0.0001 | L15: =(B15/B14)-1 -> 0 | M15: =(C15/C14)-1 -> 0 | N15: =(D15/D14)-1 -> 0 | O15: =(E15/E14)-1 -> -0.01540044 | P15: =(F15/F14)-1 -> -0.022222222
A16: 44221 | B16: 0.1 | C16: 0.13 | D16: 0.17 | E16: 0.29528304 | F16: 0.42 | G16: =(B16-B15)/100 -> 0 | H16: =(C16-C15)/100 -> 0 | I16: =(D16-D15)/100 -> -0.0002 | J16: =(E16-E15)/100 -> -0.00020206532 | K16: =(F16-F15)/100 -> -0.0002 | L16: =(B16/B15)-1 -> 0 | M16: =(C16/C15)-1 -> 0 | N16: =(D16/D15)-1 -> -0.10526316 | O16: =(E16/E15)-1 -> -0.064048178 | P16: =(F16/F15)-1 -> -0.045454545
... A603: 45072 | B603: 5.25 | C603: 4.54 | D603: 4.23 | E603: 4.0319 | F603: 3.92 | G603: =(B603-B602)/100 -> 0.0001 | H603: =(C603-C602)/100 -> 0.0004 | I603: =(D603-D602)/100 -> 0.0002 | J603: =(E603-E602)/100 -> 0.000437 | K603: =(F603-F602)/100 -> 0.0002 | L603: =(B603/B602)-1 -> 0.0019083969 | M603: =(C603/C602)-1 -> 0.0088888889 | N603: =(D603/D602)-1 -> 0.0047505938 | O603: =(E603/E602)-1 -> 0.010957324 | P603: =(F603/F602)-1 -> 0.0051282051
A604: 45076 | B604: 5.22 | C604: 4.46 | D604: 4.1 | E604: =NA() -> #N/A | F604: 3.81 | G604: =(B604-B603)/100 -> -0.0003 | H604: =(C604-C603)/100 -> -0.0008 | I604: =(D604-D603)/100 -> -0.0013 | J604: =(E604-E603)/100 -> #N/A | K604: =(F604-F603)/100 -> -0.0011 | L604: =(B604/B603)-1 -> -0.0057142857 | M604: =(C604/C603)-1 -> -0.017621145 | N604: =(D604/D603)-1 -> -0.030732861 | O604: =(E604/E603)-1 -> #N/A | P604: =(F604/F603)-1 -> -0.028061224
A605: 45077 | B605: 5.18 | C605: 4.4 | D605: 4.04 | E605: 3.9667 | F605: 3.74 | G605: =(B605-B604)/100 -> -0.0004 | H605: =(C605-C604)/100 -> -0.0006 | I605: =(D605-D604)/100 -> -0.0006 | J605: =(E605-E604)/100 -> #N/A | K605: =(F605-F604)/100 -> -0.0007 | L605: =(B605/B604)-1 -> -0.0076628352 | M605: =(C605/C604)-1 -> -0.013452915 | N605: =(D605/D604)-1 -> -0.014634146 | O605: =(E605/E604)-1 -> #N/A | P605: =(F605/F604)-1 -> -0.018372703
A606: 45078 | B606: 5.11 | C606: 4.33 | D606: 3.98 | E606: 3.8934 | F606: 3.7 | G606: =(B606-B605)/100 -> -0.0007 | H606: =(C606-C605)/100 -> -0.0007 | I606: =(D606-D605)/100 -> -0.0006 | J606: =(E606-E605)/100 -> -0.000733 | K606: =(F606-F605)/100 -> -0.0004 | L606: =(B606/B605)-1 -> -0.013513514 | M606: =(C606/C605)-1 -> -0.015909091 | N606: =(D606/D605)-1 -> -0.014851485 | O606: =(E606/E605)-1 -> -0.018478836 | P606: =(F606/F605)-1 -> -0.010695187
A607: 45079 | B607: 5.22 | C607: 4.5 | D607: 4.13 | E607: 3.8398 | F607: 3.84 | G607: =(B607-B606)/100 -> 0.0011 | H607: =(C607-C606)/100 -> 0.0017 | I607: =(D607-D606)/100 -> 0.0015 | J607: =(E607-E606)/100 -> -0.000536 | K607: =(F607-F606)/100 -> 0.0014 | L607: =(B607/B606)-1 -> 0.021526419 | M607: =(C607/C606)-1 -> 0.03926097 | N607: =(D607/D606)-1 -> 0.037688442 | O607: =(E607/E606)-1 -> -0.013766888 | P607: =(F607/F606)-1 -> 0.037837838
A608: 45082 | B608: 5.17 | C608: 4.46 | D608: 4.1 | E608: 3.931 | F608: 3.82 | G608: =(B608-B607)/100 -> -0.0005 | H608: =(C608-C607)/100 -> -0.0004 | I608: =(D608-D607)/100 -> -0.0003 | J608: =(E608-E607)/100 -> 0.000912 | K608: =(F608-F607)/100 -> -0.0002 | L608: =(B608/B607)-1 -> -0.0095785441 | M608: =(C608/C607)-1 -> -0.0088888889 | N608: =(D608/D607)-1 -> -0.0072639225 | O608: =(E608/E607)-1 -> 0.023751237 | P608: =(F608/F607)-1 -> -0.0052083333
A609: 45083 | B609: 5.2 | C609: 4.51 | D609: 4.15 | E609: 3.9351 | F609: 3.85 | G609: =(B609-B608)/100 -> 0.0003 | H609: =(C609-C608)/100 -> 0.0005 | I609: =(D609-D608)/100 -> 0.0005 | J609: =(E609-E608)/100 -> 4.1e-05 | K609: =(F609-F608)/100 -> 0.0003 | L609: =(B609/B608)-1 -> 0.0058027079 | M609: =(C609/C608)-1 -> 0.011210762 | N609: =(D609/D608)-1 -> 0.012195122 | O609: =(E609/E608)-1 -> 0.0010429916 | P609: =(F609/F608)-1 -> 0.0078534031
A610: 45084 | B610: 5.16 | C610: 4.56 | D610: 4.21 | E610: 3.9544 | F610: 3.93 | G610: =(B610-B609)/100 -> -0.0004 | H610: =(C610-C609)/100 -> 0.0005 | I610: =(D610-D609)/100 -> 0.0006 | J610: =(E610-E609)/100 -> 0.000193 | K610: =(F610-F609)/100 -> 0.0008 | L610: =(B610/B609)-1 -> -0.0076923077 | M610: =(C610/C609)-1 -> 0.011086475 | N610: =(D610/D609)-1 -> 0.014457831 | O610: =(E610/E609)-1 -> 0.0049045768 | P610: =(F610/F609)-1 -> 0.020779221
A611: 45085 | B611: 5.12 | C611: 4.52 | D611: 4.17 | E611: 4.0221 | F611: 3.87 | G611: =(B611-B610)/100 -> -0.0004 | H611: =(C611-C610)/100 -> -0.0004 | I611: =(D611-D610)/100 -> -0.0004 | J611: =(E611-E610)/100 -> 0.000677 | K611: =(F611-F610)/100 -> -0.0006 | L611: =(B611/B610)-1 -> -0.007751938 | M611: =(C611/C610)-1 -> -0.0087719298 | N611: =(D611/D610)-1 -> -0.0095011876 | O611: =(E611/E610)-1 -> 0.01712017 | P611: =(F611/F610)-1 -> -0.015267176
A612: 45086 | B612: 5.17 | C612: 4.59 | D612: 4.23 | E612: 3.9916 | F612: 3.92 | G612: =(B612-B611)/100 -> 0.0005 | H612: =(C612-C611)/100 -> 0.0007 | I612: =(D612-D611)/100 -> 0.0006 | J612: =(E612-E611)/100 -> -0.000305 | K612: =(F612-F611)/100 -> 0.0005 | L612: =(B612/B611)-1 -> 0.009765625 | M612: =(C612/C611)-1 -> 0.015486726 | N612: =(D612/D611)-1 -> 0.014388489 | O612: =(E612/E611)-1 -> -0.0075831034 | P612: =(F612/F611)-1 -> 0.012919897
A613: 45089 | B613: 5.18 | C613: 4.55 | D613: 4.16 | E613: 4.0272 | F613: 3.89 | G613: =(B613-B612)/100 -> 0.0001 | H613: =(C613-C612)/100 -> -0.0004 | I613: =(D613-D612)/100 -> -0.0007 | J613: =(E613-E612)/100 -> 0.000356 | K613: =(F613-F612)/100 -> -0.0003 | L613: =(B613/B612)-1 -> 0.001934236 | M613: =(C613/C612)-1 -> -0.0087145969 | N613: =(D613/D612)-1 -> -0.016548463 | O613: =(E613/E612)-1 -> 0.0089187293 | P613: =(F613/F612)-1 -> -0.0076530612
A614: 45090 | B614: 5.26 | C614: 4.67 | D614: 4.3 | E614: 4.0225 | F614: 4.01 | G614: =(B614-B613)/100 -> 0.0008 | H614: =(C614-C613)/100 -> 0.0012 | I614: =(D614-D613)/100 -> 0.0014 | J614: =(E614-E613)/100 -> -4.7e-05 | K614: =(F614-F613)/100 -> 0.0012 | L614: =(B614/B613)-1 -> 0.015444015 | M614: =(C614/C613)-1 -> 0.026373626 | N614: =(D614/D613)-1 -> 0.033653846 | O614: =(E614/E613)-1 -> -0.001167064 | P614: =(F614/F613)-1 -> 0.030848329
A615: 45091 | B615: 5.27 | C615: 4.74 | D615: 4.37 | E615: 4.1091 | F615: 4.06 | G615: =(B615-B614)/100 -> 0.0001 | H615: =(C615-C614)/100 -> 0.0007 | I615: =(D615-D614)/100 -> 0.0007 | J615: =(E615-E614)/100 -> 0.000866 | K615: =(F615-F614)/100 -> 0.0005 | L615: =(B615/B614)-1 -> 0.0019011407 | M615: =(C615/C614)-1 -> 0.014989293 | N615: =(D615/D614)-1 -> 0.01627907 | O615: =(E615/E614)-1 -> 0.0215289 | P615: =(F615/F614)-1 -> 0.012468828
A616: 45092 | B616: 5.21 | C616: 4.62 | D616: 4.23 | E616: 4.1583 | F616: 3.91 | G616: =(B616-B615)/100 -> -0.0006 | H616: =(C616-C615)/100 -> -0.0012 | I616: =(D616-D615)/100 -> -0.0014 | J616: =(E616-E615)/100 -> 0.000492 | K616: =(F616-F615)/100 -> -0.0015 | L616: =(B616/B615)-1 -> -0.011385199 | M616: =(C616/C615)-1 -> -0.025316456 | N616: =(D616/D615)-1 -> -0.032036613 | O616: =(E616/E615)-1 -> 0.011973425 | P616: =(F616/F615)-1 -> -0.036945813
... A618: 45097 | B618: 5.24 | C618: 4.68 | D618: 4.29 | E618: 4.1147 | F618: 3.96 | G618: =(B618-B617)/100 -> 0 | H618: =(C618-C617)/100 -> -0.0002 | I618: =(D618-D617)/100 -> -0.0003 | J618: =(E618-E617)/100 -> 0.000381 | K618: =(F618-F617)/100 -> -0.0003 | L618: =(B618/B617)-1 -> 0 | M618: =(C618/C617)-1 -> -0.0042553191 | N618: =(D618/D617)-1 -> -0.0069444444 | O618: =(E618/E617)-1 -> 0.0093460236 | P618: =(F618/F617)-1 -> -0.007518797
A619: 45098 | B619: 5.25 | C619: 4.68 | D619: 4.29 | E619: =NA() -> #N/A | F619: 3.95 | G619: =(B619-B618)/100 -> 0.0001 | H619: =(C619-C618)/100 -> 0 | I619: =(D619-D618)/100 -> 0 | J619: =(E619-E618)/100 -> #N/A | K619: =(F619-F618)/100 -> -0.0001 | L619: =(B619/B618)-1 -> 0.0019083969 | M619: =(C619/C618)-1 -> 0 | N619: =(D619/D618)-1 -> 0 | O619: =(E619/E618)-1 -> #N/A | P619: =(F619/F618)-1 -> -0.0025252525
A620: 45099 | B620: 5.29 | C620: 4.77 | D620: 4.37 | E620: 4.1085 | F620: 4.03 | G620: =(B620-B619)/100 -> 0.0004 | H620: =(C620-C619)/100 -> 0.0009 | I620: =(D620-D619)/100 -> 0.0008 | J620: =(E620-E619)/100 -> #N/A | K620: =(F620-F619)/100 -> 0.0008 | L620: =(B620/B619)-1 -> 0.0076190476 | M620: =(C620/C619)-1 -> 0.019230769 | N620: =(D620/D619)-1 -> 0.018648019 | O620: =(E620/E619)-1 -> #N/A | P620: =(F620/F619)-1 -> 0.020253165
A621: 45100 | B621: 5.25 | C621: 4.71 | D621: 4.32 | E621: 4.0994 | F621: 3.99 | G621: =(B621-B620)/100 -> -0.0004 | H621: =(C621-C620)/100 -> -0.0006 | I621: =(D621-D620)/100 -> -0.0005 | J621: =(E621-E620)/100 -> -9.1e-05 | K621: =(F621-F620)/100 -> -0.0004 | L621: =(B621/B620)-1 -> -0.0075614367 | M621: =(C621/C620)-1 -> -0.012578616 | N621: =(D621/D620)-1 -> -0.011441648 | O621: =(E621/E620)-1 -> -0.0022149203 | P621: =(F621/F620)-1 -> -0.0099255583
A622: 45103 | B622: 5.27 | C622: 4.65 | D622: 4.3 | E622: 4.1591 | F622: 3.96 | G622: =(B622-B621)/100 -> 0.0002 | H622: =(C622-C621)/100 -> -0.0006 | I622: =(D622-D621)/100 -> -0.0002 | J622: =(E622-E621)/100 -> 0.000597 | K622: =(F622-F621)/100 -> -0.0003 | L622: =(B622/B621)-1 -> 0.0038095238 | M622: =(C622/C621)-1 -> -0.012738854 | N622: =(D622/D621)-1 -> -0.0046296296 | O622: =(E622/E621)-1 -> 0.014563107 | P622: =(F622/F621)-1 -> -0.007518797
A623: 45104 | B623: 5.33 | C623: 4.74 | D623: 4.38 | E623: 4.1442 | F623: 4.02 | G623: =(B623-B622)/100 -> 0.0006 | H623: =(C623-C622)/100 -> 0.0009 | I623: =(D623-D622)/100 -> 0.0008 | J623: =(E623-E622)/100 -> -0.000149 | K623: =(F623-F622)/100 -> 0.0006 | L623: =(B623/B622)-1 -> 0.011385199 | M623: =(C623/C622)-1 -> 0.019354839 | N623: =(D623/D622)-1 -> 0.018604651 | O623: =(E623/E622)-1 -> -0.0035825058 | P623: =(F623/F622)-1 -> 0.015151515
A624: 45105 | B624: 5.32 | C624: 4.71 | D624: 4.32 | E624: 4.1258 | F624: 3.97 | G624: =(B624-B623)/100 -> -0.0001 | H624: =(C624-C623)/100 -> -0.0003 | I624: =(D624-D623)/100 -> -0.0006 | J624: =(E624-E623)/100 -> -0.000184 | K624: =(F624-F623)/100 -> -0.0005 | L624: =(B624/B623)-1 -> -0.0018761726 | M624: =(C624/C623)-1 -> -0.0063291139 | N624: =(D624/D623)-1 -> -0.01369863 | O624: =(E624/E623)-1 -> -0.0044399402 | P624: =(F624/F623)-1 -> -0.012437811
A625: 45106 | B625: 5.41 | C625: 4.87 | D625: 4.49 | E625: 4.1668 | F625: 4.14 | G625: =(B625-B624)/100 -> 0.0009 | H625: =(C625-C624)/100 -> 0.0016 | I625: =(D625-D624)/100 -> 0.0017 | J625: =(E625-E624)/100 -> 0.00041 | K625: =(F625-F624)/100 -> 0.0017 | L625: =(B625/B624)-1 -> 0.016917293 | M625: =(C625/C624)-1 -> 0.033970276 | N625: =(D625/D624)-1 -> 0.039351852 | O625: =(E625/E624)-1 -> 0.0099374667 | P625: =(F625/F624)-1 -> 0.042821159
A626: 45107 | B626: 5.4 | C626: 4.87 | D626: 4.49 | E626: 4.1367 | F626: 4.13 | G626: =(B626-B625)/100 -> -0.0001 | H626: =(C626-C625)/100 -> 0 | I626: =(D626-D625)/100 -> 0 | J626: =(E626-E625)/100 -> -0.000301 | K626: =(F626-F625)/100 -> -0.0001 | L626: =(B626/B625)-1 -> -0.0018484288 | M626: =(C626/C625)-1 -> 0 | N626: =(D626/D625)-1 -> 0 | O626: =(E626/E625)-1 -> -0.0072237688 | P626: =(F626/F625)-1 -> -0.0024154589
A627: 45110 | B627: 5.43 | C627: 4.94 | D627: 4.56 | E627: 4.2738 | F627: 4.19 | G627: =(B627-B626)/100 -> 0.0003 | H627: =(C627-C626)/100 -> 0.0007 | I627: =(D627-D626)/100 -> 0.0007 | J627: =(E627-E626)/100 -> 0.001371 | K627: =(F627-F626)/100 -> 0.0006 | L627: =(B627/B626)-1 -> 0.0055555556 | M627: =(C627/C626)-1 -> 0.014373717 | N627: =(D627/D626)-1 -> 0.0155902 | O627: =(E627/E626)-1 -> 0.03314236 | P627: =(F627/F626)-1 -> 0.014527845
A628: 45112 | B628: 5.4 | C628: 4.94 | D628: 4.59 | E628: 4.2908 | F628: 4.25 | G628: =(B628-B627)/100 -> -0.0003 | H628: =(C628-C627)/100 -> 0 | I628: =(D628-D627)/100 -> 0.0003 | J628: =(E628-E627)/100 -> 0.00017 | K628: =(F628-F627)/100 -> 0.0006 | L628: =(B628/B627)-1 -> -0.0055248619 | M628: =(C628/C627)-1 -> 0 | N628: =(D628/D627)-1 -> 0.0065789474 | O628: =(E628/E627)-1 -> 0.0039777247 | P628: =(F628/F627)-1 -> 0.014319809
A629: 45113 | B629: 5.44 | C629: 4.99 | D629: 4.68 | E629: 4.3447 | F629: 4.37 | G629: =(B629-B628)/100 -> 0.0004 | H629: =(C629-C628)/100 -> 0.0005 | I629: =(D629-D628)/100 -> 0.0009 | J629: =(E629-E628)/100 -> 0.000539 | K629: =(F629-F628)/100 -> 0.0012 | L629: =(B629/B628)-1 -> 0.0074074074 | M629: =(C629/C628)-1 -> 0.010121457 | N629: =(D629/D628)-1 -> 0.019607843 | O629: =(E629/E628)-1 -> 0.01256176 | P629: =(F629/F628)-1 -> 0.028235294
A630: 45114 | B630: 5.41 | C630: 4.94 | D630: 4.64 | E630: =NA() -> #N/A | F630: 4.35 | G630: =(B630-B629)/100 -> -0.0003 | H630: =(C630-C629)/100 -> -0.0005 | I630: =(D630-D629)/100 -> -0.0004 | J630: =(E630-E629)/100 -> #N/A | K630: =(F630-F629)/100 -> -0.0002 | L630: =(B630/B629)-1 -> -0.0055147059 | M630: =(C630/C629)-1 -> -0.01002004 | N630: =(D630/D629)-1 -> -0.0085470085 | O630: =(E630/E629)-1 -> #N/A | P630: =(F630/F629)-1 -> -0.004576659
A631: 45117 | B631: 5.38 | C631: 4.85 | D631: 4.54 | E631: 4.3905 | F631: 4.25 | G631: =(B631-B630)/100 -> -0.0003 | H631: =(C631-C630)/100 -> -0.0009 | I631: =(D631-D630)/100 -> -0.001 | J631: =(E631-E630)/100 -> #N/A | K631: =(F631-F630)/100 -> -0.001 | L631: =(B631/B630)-1 -> -0.0055452865 | M631: =(C631/C630)-1 -> -0.018218623 | N631: =(D631/D630)-1 -> -0.021551724 | O631: =(E631/E630)-1 -> #N/A | P631: =(F631/F630)-1 -> -0.022988506
A632: 45118 | B632: 5.44 | C632: 4.88 | D632: 4.52 | E632: 4.475 | F632: 4.24 | G632: =(B632-B631)/100 -> 0.0006 | H632: =(C632-C631)/100 -> 0.0003 | I632: =(D632-D631)/100 -> -0.0002 | J632: =(E632-E631)/100 -> 0.000845 | K632: =(F632-F631)/100 -> -0.0001 | L632: =(B632/B631)-1 -> 0.011152416 | M632: =(C632/C631)-1 -> 0.006185567 | N632: =(D632/D631)-1 -> -0.0044052863 | O632: =(E632/E631)-1 -> 0.0192461 | P632: =(F632/F631)-1 -> -0.0023529412
A633: 45119 | B633: 5.35 | C633: 4.72 | D633: 4.36 | E633: 4.4741 | F633: 4.07 | G633: =(B633-B632)/100 -> -0.0009 | H633: =(C633-C632)/100 -> -0.0016 | I633: =(D633-D632)/100 -> -0.0016 | J633: =(E633-E632)/100 -> -9e-06 | K633: =(F633-F632)/100 -> -0.0017 | L633: =(B633/B632)-1 -> -0.016544118 | M633: =(C633/C632)-1 -> -0.032786885 | N633: =(D633/D632)-1 -> -0.03539823 | O633: =(E633/E632)-1 -> -0.00020111732 | P633: =(F633/F632)-1 -> -0.04009434
A634: 45120 | B634: 5.27 | C634: 4.59 | D634: 4.21 | E634: 4.3996 | F634: 3.93 | G634: =(B634-B633)/100 -> -0.0008 | H634: =(C634-C633)/100 -> -0.0013 | I634: =(D634-D633)/100 -> -0.0015 | J634: =(E634-E633)/100 -> -0.000745 | K634: =(F634-F633)/100 -> -0.0014 | L634: =(B634/B633)-1 -> -0.014953271 | M634: =(C634/C633)-1 -> -0.027542373 | N634: =(D634/D633)-1 -> -0.03440367 | O634: =(E634/E633)-1 -> -0.016651394 | P634: =(F634/F633)-1 -> -0.034398034
A635: 45121 | B635: 5.34 | C635: 4.74 | D635: 4.35 | E635: 4.378 | F635: 4.04 | G635: =(B635-B634)/100 -> 0.0007 | H635: =(C635-C634)/100 -> 0.0015 | I635: =(D635-D634)/100 -> 0.0014 | J635: =(E635-E634)/100 -> -0.000216 | K635: =(F635-F634)/100 -> 0.0011 | L635: =(B635/B634)-1 -> 0.013282732 | M635: =(C635/C634)-1 -> 0.032679739 | N635: =(D635/D634)-1 -> 0.033254157 | O635: =(E635/E634)-1 -> -0.0049095372 | P635: =(F635/F634)-1 -> 0.027989822
A636: 45124 | B636: 5.33 | C636: 4.74 | D636: 4.34 | E636: 4.2483 | F636: 4.02 | G636: =(B636-B635)/100 -> -0.0001 | H636: =(C636-C635)/100 -> 0 | I636: =(D636-D635)/100 -> -0.0001 | J636: =(E636-E635)/100 -> -0.001297 | K636: =(F636-F635)/100 -> -0.0002 | L636: =(B636/B635)-1 -> -0.0018726592 | M636: =(C636/C635)-1 -> 0 | N636: =(D636/D635)-1 -> -0.0022988506 | O636: =(E636/E635)-1 -> -0.0296254 | P636: =(F636/F635)-1 -> -0.004950495
A637: 45125 | B637: 5.32 | C637: 4.74 | D637: 4.35 | E637: 4.1146 | F637: 4 | G637: =(B637-B636)/100 -> -0.0001 | H637: =(C637-C636)/100 -> 0 | I637: =(D637-D636)/100 -> 0.0001 | J637: =(E637-E636)/100 -> -0.001337 | K637: =(F637-F636)/100 -> -0.0002 | L637: =(B637/B636)-1 -> -0.0018761726 | M637: =(C637/C636)-1 -> 0 | N637: =(D637/D636)-1 -> 0.0023041475 | O637: =(E637/E636)-1 -> -0.031471412 | P637: =(F637/F636)-1 -> -0.0049751244
A638: 45126 | B638: 5.32 | C638: 4.74 | D638: 4.34 | E638: 4.1582 | F638: 3.98 | G638: =(B638-B637)/100 -> 0 | H638: =(C638-C637)/100 -> 0 | I638: =(D638-D637)/100 -> -0.0001 | J638: =(E638-E637)/100 -> 0.000436 | K638: =(F638-F637)/100 -> -0.0002 | L638: =(B638/B637)-1 -> 0 | M638: =(C638/C637)-1 -> 0 | N638: =(D638/D637)-1 -> -0.0022988506 | O638: =(E638/E637)-1 -> 0.010596413 | P638: =(F638/F637)-1 -> -0.005
A639: 45127 | B639: 5.35 | C639: 4.8 | D639: 4.43 | E639: 4.1516 | F639: 4.08 | G639: =(B639-B638)/100 -> 0.0003 | H639: =(C639-C638)/100 -> 0.0006 | I639: =(D639-D638)/100 -> 0.0009 | J639: =(E639-E638)/100 -> -6.6e-05 | K639: =(F639-F638)/100 -> 0.001 | L639: =(B639/B638)-1 -> 0.0056390977 | M639: =(C639/C638)-1 -> 0.012658228 | N639: =(D639/D638)-1 -> 0.020737327 | O639: =(E639/E638)-1 -> -0.0015872252 | P639: =(F639/F638)-1 -> 0.025125628
A640: 45128 | B640: 5.35 | C640: 4.82 | D640: 4.44 | E640: 4.1413 | F640: 4.09 | G640: =(B640-B639)/100 -> 0 | H640: =(C640-C639)/100 -> 0.0002 | I640: =(D640-D639)/100 -> 0.0001 | J640: =(E640-E639)/100 -> -0.000103 | K640: =(F640-F639)/100 -> 0.0001 | L640: =(B640/B639)-1 -> 0 | M640: =(C640/C639)-1 -> 0.0041666667 | N640: =(D640/D639)-1 -> 0.0022573363 | O640: =(E640/E639)-1 -> -0.0024809712 | P640: =(F640/F639)-1 -> 0.0024509804
A641: 45131 | B641: 5.38 | C641: 4.81 | D641: 4.48 | E641: 4.1204 | F641: 4.13 | G641: =(B641-B640)/100 -> 0.0003 | H641: =(C641-C640)/100 -> -0.0001 | I641: =(D641-D640)/100 -> 0.0004 | J641: =(E641-E640)/100 -> -0.000209 | K641: =(F641-F640)/100 -> 0.0004 | L641: =(B641/B640)-1 -> 0.0056074766 | M641: =(C641/C640)-1 -> -0.0020746888 | N641: =(D641/D640)-1 -> 0.009009009 | O641: =(E641/E640)-1 -> -0.0050467245 | P641: =(F641/F640)-1 -> 0.0097799511
A642: 45132 | B642: 5.38 | C642: 4.85 | D642: 4.53 | E642: 4.1888 | F642: 4.15 | G642: =(B642-B641)/100 -> 0 | H642: =(C642-C641)/100 -> 0.0004 | I642: =(D642-D641)/100 -> 0.0005 | J642: =(E642-E641)/100 -> 0.000684 | K642: =(F642-F641)/100 -> 0.0002 | L642: =(B642/B641)-1 -> 0 | M642: =(C642/C641)-1 -> 0.0083160083 | N642: =(D642/D641)-1 -> 0.011160714 | O642: =(E642/E641)-1 -> 0.01660033 | P642: =(F642/F641)-1 -> 0.004842615
... A673: 45176 | B673: 5.4 | C673: 4.94 | D673: 4.66 | E673: 4.3956 | F673: 4.38 | G673: =(B673-B672)/100 -> -0.0004 | H673: =(C673-C672)/100 -> -0.0007 | I673: =(D673-D672)/100 -> -0.0007 | J673: =(E673-E672)/100 -> 0.000318 | K673: =(F673-F672)/100 -> -0.0006 | L673: =(B673/B672)-1 -> -0.0073529412 | M673: =(C673/C672)-1 -> -0.013972056 | N673: =(D673/D672)-1 -> -0.014799154 | O673: =(E673/E672)-1 -> 0.0072872267 | P673: =(F673/F672)-1 -> -0.013513514
A674: 45177 | B674: 5.42 | C674: 4.98 | D674: 4.68 | E674: =NA() -> #N/A | F674: 4.39 | G674: =(B674-B673)/100 -> 0.0002 | H674: =(C674-C673)/100 -> 0.0004 | I674: =(D674-D673)/100 -> 0.0002 | J674: =(E674-E673)/100 -> #N/A | K674: =(F674-F673)/100 -> 0.0001 | L674: =(B674/B673)-1 -> 0.0037037037 | M674: =(C674/C673)-1 -> 0.008097166 | N674: =(D674/D673)-1 -> 0.0042918455 | O674: =(E674/E673)-1 -> #N/A | P674: =(F674/F673)-1 -> 0.002283105
A675: 45180 | B675: 5.4 | C675: 4.97 | D675: 4.64 | E675: 4.4646 | F675: 4.4 | G675: =(B675-B674)/100 -> -0.0002 | H675: =(C675-C674)/100 -> -0.0001 | I675: =(D675-D674)/100 -> -0.0004 | J675: =(E675-E674)/100 -> #N/A | K675: =(F675-F674)/100 -> 0.0001 | L675: =(B675/B674)-1 -> -0.0036900369 | M675: =(C675/C674)-1 -> -0.0020080321 | N675: =(D675/D674)-1 -> -0.0085470085 | O675: =(E675/E674)-1 -> #N/A | P675: =(F675/F674)-1 -> 0.0022779043
A676: 45181 | B676: 5.42 | C676: 4.98 | D676: 4.66 | E676: 4.5395 | F676: 4.41 | G676: =(B676-B675)/100 -> 0.0002 | H676: =(C676-C675)/100 -> 0.0001 | I676: =(D676-D675)/100 -> 0.0002 | J676: =(E676-E675)/100 -> 0.000749 | K676: =(F676-F675)/100 -> 0.0001 | L676: =(B676/B675)-1 -> 0.0037037037 | M676: =(C676/C675)-1 -> 0.0020120724 | N676: =(D676/D675)-1 -> 0.0043103448 | O676: =(E676/E675)-1 -> 0.016776419 | P676: =(F676/F675)-1 -> 0.0022727273
A677: 45182 | B677: 5.42 | C677: 4.96 | D677: 4.64 | E677: 4.4953 | F677: 4.39 | G677: =(B677-B676)/100 -> 0 | H677: =(C677-C676)/100 -> -0.0002 | I677: =(D677-D676)/100 -> -0.0002 | J677: =(E677-E676)/100 -> -0.000442 | K677: =(F677-F676)/100 -> -0.0002 | L677: =(B677/B676)-1 -> 0 | M677: =(C677/C676)-1 -> -0.0040160643 | N677: =(D677/D676)-1 -> -0.0042918455 | O677: =(E677/E676)-1 -> -0.0097367551 | P677: =(F677/F676)-1 -> -0.0045351474
A678: 45183 | B678: 5.42 | C678: 5 | D678: 4.68 | E678: 4.4921 | F678: 4.42 | G678: =(B678-B677)/100 -> 0 | H678: =(C678-C677)/100 -> 0.0004 | I678: =(D678-D677)/100 -> 0.0004 | J678: =(E678-E677)/100 -> -3.2e-05 | K678: =(F678-F677)/100 -> 0.0003 | L678: =(B678/B677)-1 -> 0 | M678: =(C678/C677)-1 -> 0.0080645161 | N678: =(D678/D677)-1 -> 0.0086206897 | O678: =(E678/E677)-1 -> -0.0007118546 | P678: =(F678/F677)-1 -> 0.006833713
A679: 45184 | B679: 5.43 | C679: 5.02 | D679: 4.72 | E679: 4.5019 | F679: 4.45 | G679: =(B679-B678)/100 -> 0.0001 | H679: =(C679-C678)/100 -> 0.0002 | I679: =(D679-D678)/100 -> 0.0004 | J679: =(E679-E678)/100 -> 9.8e-05 | K679: =(F679-F678)/100 -> 0.0003 | L679: =(B679/B678)-1 -> 0.0018450185 | M679: =(C679/C678)-1 -> 0.004 | N679: =(D679/D678)-1 -> 0.0085470085 | O679: =(E679/E678)-1 -> 0.0021816077 | P679: =(F679/F678)-1 -> 0.0067873303
A680: 45187 | B680: 5.44 | C680: 5.05 | D680: 4.74 | E680: 4.5061 | F680: 4.46 | G680: =(B680-B679)/100 -> 0.0001 | H680: =(C680-C679)/100 -> 0.0003 | I680: =(D680-D679)/100 -> 0.0002 | J680: =(E680-E679)/100 -> 4.2e-05 | K680: =(F680-F679)/100 -> 0.0001 | L680: =(B680/B679)-1 -> 0.0018416206 | M680: =(C680/C679)-1 -> 0.0059760956 | N680: =(D680/D679)-1 -> 0.0042372881 | O680: =(E680/E679)-1 -> 0.00093293943 | P680: =(F680/F679)-1 -> 0.002247191
A681: 45188 | B681: 5.45 | C681: 5.08 | D681: 4.79 | E681: 4.491 | F681: 4.51 | G681: =(B681-B680)/100 -> 0.0001 | H681: =(C681-C680)/100 -> 0.0003 | I681: =(D681-D680)/100 -> 0.0005 | J681: =(E681-E680)/100 -> -0.000151 | K681: =(F681-F680)/100 -> 0.0005 | L681: =(B681/B680)-1 -> 0.0018382353 | M681: =(C681/C680)-1 -> 0.0059405941 | N681: =(D681/D680)-1 -> 0.010548523 | O681: =(E681/E680)-1 -> -0.0033510131 | P681: =(F681/F680)-1 -> 0.011210762
A682: 45189 | B682: 5.47 | C682: 5.12 | D682: 4.82 | E682: 4.5104 | F682: 4.52 | G682: =(B682-B681)/100 -> 0.0002 | H682: =(C682-C681)/100 -> 0.0004 | I682: =(D682-D681)/100 -> 0.0003 | J682: =(E682-E681)/100 -> 0.000194 | K682: =(F682-F681)/100 -> 0.0001 | L682: =(B682/B681)-1 -> 0.0036697248 | M682: =(C682/C681)-1 -> 0.0078740157 | N682: =(D682/D681)-1 -> 0.006263048 | O682: =(E682/E681)-1 -> 0.0043197506 | P682: =(F682/F681)-1 -> 0.0022172949
A683: 45190 | B683: 5.46 | C683: 5.12 | D683: 4.85 | E683: 4.5575 | F683: 4.61 | G683: =(B683-B682)/100 -> -0.0001 | H683: =(C683-C682)/100 -> 0 | I683: =(D683-D682)/100 -> 0.0003 | J683: =(E683-E682)/100 -> 0.000471 | K683: =(F683-F682)/100 -> 0.0009 | L683: =(B683/B682)-1 -> -0.0018281536 | M683: =(C683/C682)-1 -> 0 | N683: =(D683/D682)-1 -> 0.0062240664 | O683: =(E683/E682)-1 -> 0.010442533 | P683: =(F683/F682)-1 -> 0.019911504
A684: 45191 | B684: 5.46 | C684: 5.1 | D684: 4.8 | E684: 4.5748 | F684: 4.57 | G684: =(B684-B683)/100 -> 0 | H684: =(C684-C683)/100 -> -0.0002 | I684: =(D684-D683)/100 -> -0.0005 | J684: =(E684-E683)/100 -> 0.000173 | K684: =(F684-F683)/100 -> -0.0004 | L684: =(B684/B683)-1 -> 0 | M684: =(C684/C683)-1 -> -0.00390625 | N684: =(D684/D683)-1 -> -0.010309278 | O684: =(E684/E683)-1 -> 0.0037959408 | P684: =(F684/F683)-1 -> -0.0086767896
A685: 45194 | B685: 5.45 | C685: 5.09 | D685: 4.83 | E685: 4.6139 | F685: 4.62 | G685: =(B685-B684)/100 -> -0.0001 | H685: =(C685-C684)/100 -> -0.0001 | I685: =(D685-D684)/100 -> 0.0003 | J685: =(E685-E684)/100 -> 0.000391 | K685: =(F685-F684)/100 -> 0.0005 | L685: =(B685/B684)-1 -> -0.0018315018 | M685: =(C685/C684)-1 -> -0.0019607843 | N685: =(D685/D684)-1 -> 0.00625 | O685: =(E685/E684)-1 -> 0.0085468217 | P685: =(F685/F684)-1 -> 0.010940919
A686: 45195 | B686: 5.45 | C686: 5.04 | D686: 4.84 | E686: 4.6242 | F686: 4.62 | G686: =(B686-B685)/100 -> 0 | H686: =(C686-C685)/100 -> -0.0005 | I686: =(D686-D685)/100 -> 0.0001 | J686: =(E686-E685)/100 -> 0.000103 | K686: =(F686-F685)/100 -> 0 | L686: =(B686/B685)-1 -> 0 | M686: =(C686/C685)-1 -> -0.0098231827 | N686: =(D686/D685)-1 -> 0.0020703934 | O686: =(E686/E685)-1 -> 0.0022323848 | P686: =(F686/F685)-1 -> 0
... A698: 45212 | B698: 5.41 | C698: 5.04 | D698: 4.8 | E698: 4.785 | F698: 4.65 | G698: =(B698-B697)/100 -> -0.0002 | H698: =(C698-C697)/100 -> -0.0002 | I698: =(D698-D697)/100 -> -0.0002 | J698: =(E698-E697)/100 -> 0.000255 | K698: =(F698-F697)/100 -> -0.0004 | L698: =(B698/B697)-1 -> -0.0036832413 | M698: =(C698/C697)-1 -> -0.0039525692 | N698: =(D698/D697)-1 -> -0.0041493776 | O698: =(E698/E697)-1 -> 0.0053577056 | P698: =(F698/F697)-1 -> -0.0085287846
A699: 45215 | B699: 5.42 | C699: 5.09 | D699: 4.87 | E699: =NA() -> #N/A | F699: 4.72 | G699: =(B699-B698)/100 -> 0.0001 | H699: =(C699-C698)/100 -> 0.0005 | I699: =(D699-D698)/100 -> 0.0007 | J699: =(E699-E698)/100 -> #N/A | K699: =(F699-F698)/100 -> 0.0007 | L699: =(B699/B698)-1 -> 0.0018484288 | M699: =(C699/C698)-1 -> 0.0099206349 | N699: =(D699/D698)-1 -> 0.014583333 | O699: =(E699/E698)-1 -> #N/A | P699: =(F699/F698)-1 -> 0.015053763
A700: 45216 | B700: 5.48 | C700: 5.19 | D700: 5.01 | E700: 4.6964 | F700: 4.86 | G700: =(B700-B699)/100 -> 0.0006 | H700: =(C700-C699)/100 -> 0.001 | I700: =(D700-D699)/100 -> 0.0014 | J700: =(E700-E699)/100 -> #N/A | K700: =(F700-F699)/100 -> 0.0014 | L700: =(B700/B699)-1 -> 0.011070111 | M700: =(C700/C699)-1 -> 0.019646365 | N700: =(D700/D699)-1 -> 0.028747433 | O700: =(E700/E699)-1 -> #N/A | P700: =(F700/F699)-1 -> 0.029661017
A701: 45217 | B701: 5.47 | C701: 5.19 | D701: 5.03 | E701: 4.649 | F701: 4.92 | G701: =(B701-B700)/100 -> -0.0001 | H701: =(C701-C700)/100 -> 0 | I701: =(D701-D700)/100 -> 0.0002 | J701: =(E701-E700)/100 -> -0.000474 | K701: =(F701-F700)/100 -> 0.0006 | L701: =(B701/B700)-1 -> -0.0018248175 | M701: =(C701/C700)-1 -> 0 | N701: =(D701/D700)-1 -> 0.003992016 | O701: =(E701/E700)-1 -> -0.010092837 | P701: =(F701/F700)-1 -> 0.012345679
A702: 45218 | B702: 5.44 | C702: 5.14 | D702: 5.01 | E702: 4.7271 | F702: 4.95 | G702: =(B702-B701)/100 -> -0.0003 | H702: =(C702-C701)/100 -> -0.0005 | I702: =(D702-D701)/100 -> -0.0002 | J702: =(E702-E701)/100 -> 0.000781 | K702: =(F702-F701)/100 -> 0.0003 | L702: =(B702/B701)-1 -> -0.0054844607 | M702: =(C702/C701)-1 -> -0.0096339114 | N702: =(D702/D701)-1 -> -0.0039761431 | O702: =(E702/E701)-1 -> 0.016799312 | P702: =(F702/F701)-1 -> 0.006097561
A703: 45219 | B703: 5.41 | C703: 5.07 | D703: 4.93 | E703: 4.7042 | F703: 4.86 | G703: =(B703-B702)/100 -> -0.0003 | H703: =(C703-C702)/100 -> -0.0007 | I703: =(D703-D702)/100 -> -0.0008 | J703: =(E703-E702)/100 -> -0.000229 | K703: =(F703-F702)/100 -> -0.0009 | L703: =(B703/B702)-1 -> -0.0055147059 | M703: =(C703/C702)-1 -> -0.013618677 | N703: =(D703/D702)-1 -> -0.015968064 | O703: =(E703/E702)-1 -> -0.0048444078 | P703: =(F703/F702)-1 -> -0.018181818
A704: 45222 | B704: 5.42 | C704: 5.05 | D704: 4.89 | E704: 4.7496 | F704: 4.81 | G704: =(B704-B703)/100 -> 0.0001 | H704: =(C704-C703)/100 -> -0.0002 | I704: =(D704-D703)/100 -> -0.0004 | J704: =(E704-E703)/100 -> 0.000454 | K704: =(F704-F703)/100 -> -0.0005 | L704: =(B704/B703)-1 -> 0.0018484288 | M704: =(C704/C703)-1 -> -0.0039447732 | N704: =(D704/D703)-1 -> -0.0081135903 | O704: =(E704/E703)-1 -> 0.0096509502 | P704: =(F704/F703)-1 -> -0.010288066
A705: 45223 | B705: 5.41 | C705: 5.02 | D705: 4.91 | E705: 4.8595 | F705: 4.82 | G705: =(B705-B704)/100 -> -0.0001 | H705: =(C705-C704)/100 -> -0.0003 | I705: =(D705-D704)/100 -> 0.0002 | J705: =(E705-E704)/100 -> 0.001099 | K705: =(F705-F704)/100 -> 0.0001 | L705: =(B705/B704)-1 -> -0.0018450185 | M705: =(C705/C704)-1 -> -0.0059405941 | N705: =(D705/D704)-1 -> 0.0040899796 | O705: =(E705/E704)-1 -> 0.023138791 | P705: =(F705/F704)-1 -> 0.0020790021
A706: 45224 | B706: 5.43 | C706: 5.08 | D706: 4.98 | E706: 4.9106 | F706: 4.89 | G706: =(B706-B705)/100 -> 0.0002 | H706: =(C706-C705)/100 -> 0.0006 | I706: =(D706-D705)/100 -> 0.0007 | J706: =(E706-E705)/100 -> 0.000511 | K706: =(F706-F705)/100 -> 0.0007 | L706: =(B706/B705)-1 -> 0.0036968577 | M706: =(C706/C705)-1 -> 0.011952191 | N706: =(D706/D705)-1 -> 0.014256619 | O706: =(E706/E705)-1 -> 0.010515485 | P706: =(F706/F705)-1 -> 0.014522822
A707: 45225 | B707: 5.39 | C707: 5.02 | D707: 4.89 | E707: 4.9375 | F707: 4.79 | G707: =(B707-B706)/100 -> -0.0004 | H707: =(C707-C706)/100 -> -0.0006 | I707: =(D707-D706)/100 -> -0.0009 | J707: =(E707-E706)/100 -> 0.000269 | K707: =(F707-F706)/100 -> -0.001 | L707: =(B707/B706)-1 -> -0.0073664825 | M707: =(C707/C706)-1 -> -0.011811024 | N707: =(D707/D706)-1 -> -0.018072289 | O707: =(E707/E706)-1 -> 0.0054779457 | P707: =(F707/F706)-1 -> -0.020449898
A708: 45226 | B708: 5.39 | C708: 4.99 | D708: 4.84 | E708: 4.8851 | F708: 4.76 | G708: =(B708-B707)/100 -> 0 | H708: =(C708-C707)/100 -> -0.0003 | I708: =(D708-D707)/100 -> -0.0005 | J708: =(E708-E707)/100 -> -0.000524 | K708: =(F708-F707)/100 -> -0.0003 | L708: =(B708/B707)-1 -> 0 | M708: =(C708/C707)-1 -> -0.0059760956 | N708: =(D708/D707)-1 -> -0.010224949 | O708: =(E708/E707)-1 -> -0.010612658 | P708: =(F708/F707)-1 -> -0.006263048
A709: 45229 | B709: 5.41 | C709: 5.03 | D709: 4.87 | E709: 4.8331 | F709: 4.8 | G709: =(B709-B708)/100 -> 0.0002 | H709: =(C709-C708)/100 -> 0.0004 | I709: =(D709-D708)/100 -> 0.0003 | J709: =(E709-E708)/100 -> -0.00052 | K709: =(F709-F708)/100 -> 0.0004 | L709: =(B709/B708)-1 -> 0.0037105751 | M709: =(C709/C708)-1 -> 0.0080160321 | N709: =(D709/D708)-1 -> 0.0061983471 | O709: =(E709/E708)-1 -> -0.010644613 | P709: =(F709/F708)-1 -> 0.0084033613
A710: 45230 | B710: 5.44 | C710: 5.07 | D710: 4.9 | E710: 4.8262 | F710: 4.82 | G710: =(B710-B709)/100 -> 0.0003 | H710: =(C710-C709)/100 -> 0.0004 | I710: =(D710-D709)/100 -> 0.0003 | J710: =(E710-E709)/100 -> -6.9e-05 | K710: =(F710-F709)/100 -> 0.0002 | L710: =(B710/B709)-1 -> 0.0055452865 | M710: =(C710/C709)-1 -> 0.0079522863 | N710: =(D710/D709)-1 -> 0.0061601643 | O710: =(E710/E709)-1 -> -0.0014276551 | P710: =(F710/F709)-1 -> 0.0041666667
A711: 45231 | B711: 5.37 | C711: 4.95 | D711: 4.76 | E711: 4.8907 | F711: 4.67 | G711: =(B711-B710)/100 -> -0.0007 | H711: =(C711-C710)/100 -> -0.0012 | I711: =(D711-D710)/100 -> -0.0014 | J711: =(E711-E710)/100 -> 0.000645 | K711: =(F711-F710)/100 -> -0.0015 | L711: =(B711/B710)-1 -> -0.012867647 | M711: =(C711/C710)-1 -> -0.023668639 | N711: =(D711/D710)-1 -> -0.028571429 | O711: =(E711/E710)-1 -> 0.013364552 | P711: =(F711/F710)-1 -> -0.031120332
... A1080: 45772 | B1080: 3.95 | C1080: 3.74 | D1080: 3.76 | E1080: 3.7865 | F1080: 3.88 | G1080: =(B1080-B1079)/100 -> -0.0002 | H1080: =(C1080-C1079)/100 -> -0.0003 | I1080: =(D1080-D1079)/100 -> -0.0004 | J1080: =(E1080-E1079)/100 -> -0.000418 | K1080: =(F1080-F1079)/100 -> -0.0003 | L1080: =(B1080/B1079)-1 -> -0.0050377834 | M1080: =(C1080/C1079)-1 -> -0.0079575597 | N1080: =(D1080/D1079)-1 -> -0.010526316 | O1080: =(E1080/E1079)-1 -> -0.010918685 | P1080: =(F1080/F1079)-1 -> -0.0076726343

Sheet Delta-Normal VaR
B2: Objective | C2: OPTION PORTFOLIO
L3: 1 | O3: 3 | S3: Insights
B4: long put | C4: NESTLE | D4: NESN | E4: 7000 | L4: σ | M4: {=SQRT((MMULT(MMULT(F11:G11,C11:D12),TRANSPOSE(F11:G11))))} -> 3657708.3 | O4: 1st percentile Return | P4: =_xlfn.PERCENTILE.INC(P18:P267,0.01) -> -0.51498906 | S4: The portfolio includes a long position in 7,000 NESN puts
B5: short call | C5: SWISS RE | D5: SREN | E5: 2000 | L5: VaR(99%,1) | M5: =_xlfn.NORM.S.INV(0.99)*M4 -> 8509101.9 | O5: VaR(99%,1) : | P5: =ABS(P4)*O17 -> 14536383 | S5: and a short position in 2,000 SREN calls, each referencing 1,000 shares.
L6: ES(99%,1) | M6: =M4*EXP(-(_xlfn.NORM.S.INV(0.99)^2)/2)/(SQRT(2*PI())*0.01) -> 9748576.1 | O6: Mean Below VaR : | P6: =AVERAGEIF(P18:P267,"<-0.514999") -> -0.63109505 | S6: Derived the 1-day risk measures:
I7: β_π | J7: σ_Market | O7: ES(99%,1) : | P7: =ABS(P6)*O17 -> 17813658 | S7: VaR(99%): CHF 14,536,382.70
I8: {=MMULT(I11:J11,Underlying_Assets!C3:C4)} -> 0.84408634 | J8: =SQRT(_xlfn.VAR.S(Underlying_Assets!K9:K295)) -> 0.0045202852 | L8: 2 | S8: ES(99%): CHF 17,813,658.16
L9: σ | M9: =SUM(F11:G11)*I8*J8 -> 1349876.7 | S9: This approach captures linear risk through deltas and provides
B10: VCV | C10: NESN | D10: SREN | F10: VALUE_NESN | G10: VALUE_SREN | I10: Weight_NESN | J10: Weight_SREN | L10: VaR(99%,1) | M10: =_xlfn.NORM.S.INV(0.99)*M9 -> 3140282.7 | S10: a fast approximation of market risk
B11: NESN | C11: =_xlfn.COVARIANCE.S(Underlying_Assets!H9:H365,Underlying_Assets!H9:H365) -> 0.00013124841 | D11: =_xlfn.COVARIANCE.S(Underlying_Assets!H9:H365,Underlying_Assets!I9:I365) -> 4.8345612e-05 | F11: =(I17-1)*Option_Portfolio!B4*1000*-1*C17 -> 2.5868236e+08 | G11: =(J17-1)*Option_Portfolio!B4*1000*-1*D17 -> 95104243 | I11: =F11/SUM($F$11:$G$11) -> 0.7311819 | J11: =G11/SUM($F$11:$G$11) -> 0.2688181 | L11: ES(99%,1) | M11: =M9*EXP(-(_xlfn.NORM.S.INV(0.99)^2)/2)/(SQRT(2*PI())*0.01) -> 3597710.5
B12: SREN | C12: =_xlfn.COVARIANCE.S(Underlying_Assets!I10:I366,Underlying_Assets!H10:H366) -> 4.8224643e-05 | D12: =_xlfn.COVARIANCE.S(Underlying_Assets!I10:I366,Underlying_Assets!I10:I366) -> 0.00024548163
B16: date | C16: P_NESN | D16: P_SREN | E16: d1_NESN | F16: d1_SREN | G16: d2_NESN | H16: d2_SREN | I16: N(d1)_NESN | J16: N(d1)_SREN | K16: N(d2)_NESN | L16: N(d2)_SREN | M16: Put_NESN | N16: Call_SREN | O16: π | P16: R_π
B17: 45407 | C17: 85.74 | D17: 144.8 | E17: =(LN(C17/Option_Portfolio!$E$4)+(Option_Portfolio!$H$4+0.5*Option_Portfolio!$G$4^2)*Option_Portfolio!$F$4)/(Option_Portfolio!$G$4*SQRT(Option_Portfolio!$F$4)) -> 0.17380855 | F17: =(LN(D17/Option_Portfolio!$E$5)+(Option_Portfolio!$H$5+0.5*Option_Portfolio!$G$5^2)*Option_Portfolio!$F$5)/(Option_Portfolio!$G$5*SQRT(Option_Portfolio!$F$5)) -> 1.3175439 | G17: =E17-Option_Portfolio!$G$4*SQRT(Option_Portfolio!$F$4) -> 0.053600397 | H17: =F17-Option_Portfolio!$G$5*SQRT(Option_Portfolio!$F$5) -> 1.1619805 | I17: =_xlfn.NORM.S.DIST(E17,TRUE) -> 0.56899204 | J17: =_xlfn.NORM.S.DIST(F17,TRUE) -> 0.90617182 | K17: =_xlfn.NORM.S.DIST(G17,TRUE) -> 0.52137323 | L17: =_xlfn.NORM.S.DIST(H17,TRUE) -> 0.8773783 | M17: =(1-K17)*Option_Portfolio!$E$4*EXP(-Option_Portfolio!$H$4*Option_Portfolio!$F$4)-(1-I17)*C17 -> 3.5257441 | N17: =J17*D17-L17*Option_Portfolio!$E$5*EXP(-Option_Portfolio!$H$5*Option_Portfolio!$F$5) -> 26.453397 | O17: =M17 * -Option_Portfolio!$B$4 * 1000 + N17 * Option_Portfolio!$B$5 * 1000 -> 28226585 | P17: 0
B18: T1 | C18: =$C$17*(1+Underlying_Assets!H9) -> 85.083217 | D18: =$D$17*(1+Underlying_Assets!I9) -> 143.15586 | E18: =(LN(C18/Option_Portfolio!$E$4)+(Option_Portfolio!$H$4+0.5*Option_Portfolio!$G$4^2)*Option_Portfolio!$F$4)/(Option_Portfolio!$G$4*SQRT(Option_Portfolio!$F$4)) -> 0.10983904 | F18: =(LN(D18/Option_Portfolio!$E$5)+(Option_Portfolio!$H$5+0.5*Option_Portfolio!$G$5^2)*Option_Portfolio!$F$5)/(Option_Portfolio!$G$5*SQRT(Option_Portfolio!$F$5)) -> 1.2441364 | G18: =E18-Option_Portfolio!$G$4*SQRT(Option_Portfolio!$F$4) -> -0.010369116 | H18: =F18-Option_Portfolio!$G$5*SQRT(Option_Portfolio!$F$5) -> 1.0885729 | I18: =_xlfn.NORM.S.DIST(E18,TRUE) -> 0.54373148 | J18: =_xlfn.NORM.S.DIST(F18,TRUE) -> 0.89327531 | K18: =_xlfn.NORM.S.DIST(G18,TRUE) -> 0.4958634 | L18: =_xlfn.NORM.S.DIST(H18,TRUE) -> 0.86182886 | M18: =(1-K18)*Option_Portfolio!$E$4*EXP(-Option_Portfolio!$H$4*Option_Portfolio!$F$4)-(1-I18)*C18 -> 3.8170948 | N18: =J18*D18-L18*Option_Portfolio!$E$5*EXP(-Option_Portfolio!$H$5*Option_Portfolio!$F$5) -> 24.973936 | O18: =M18 * -Option_Portfolio!$B$4 * 1000 + N18 * Option_Portfolio!$B$5 * 1000 -> 23228208 | P18: =(O18/O17)-1 -> -0.17708047
B19: T2 | C19: =$C$17*(1+Underlying_Assets!H10) -> 85.843146 | D19: =$D$17*(1+Underlying_Assets!I10) -> 144.56659 | E19: =(LN(C19/Option_Portfolio!$E$4)+(Option_Portfolio!$H$4+0.5*Option_Portfolio!$G$4^2)*Option_Portfolio!$F$4)/(Option_Portfolio!$G$4*SQRT(Option_Portfolio!$F$4)) -> 0.18381024 | F19: =(LN(D19/Option_Portfolio!$E$5)+(Option_Portfolio!$H$5+0.5*Option_Portfolio!$G$5^2)*Option_Portfolio!$F$5)/(Option_Portfolio!$G$5*SQRT(Option_Portfolio!$F$5)) -> 1.3071737 | G19: =E19-Option_Portfolio!$G$4*SQRT(Option_Portfolio!$F$4) -> 0.063602085 | H19: =F19-Option_Portfolio!$G$5*SQRT(Option_Portfolio!$F$5) -> 1.1516102 | I19: =_xlfn.NORM.S.DIST(E19,TRUE) -> 0.57291884 | J19: =_xlfn.NORM.S.DIST(F19,TRUE) -> 0.90442314 | K19: =_xlfn.NORM.S.DIST(G19,TRUE) -> 0.52535646 | L19: =_xlfn.NORM.S.DIST(H19,TRUE) -> 0.87525936 | M19: =(1-K19)*Option_Portfolio!$E$4*EXP(-Option_Portfolio!$H$4*Option_Portfolio!$F$4)-(1-I19)*C19 -> 3.48149 | N19: =J19*D19-L19*Option_Portfolio!$E$5*EXP(-Option_Portfolio!$H$5*Option_Portfolio!$F$5) -> 26.242093 | O19: =M19 * -Option_Portfolio!$B$4 * 1000 + N19 * Option_Portfolio!$B$5 * 1000 -> 28113757 | P19: =(O19/O18)-1 -> 0.21032826
B20: T3 | C20: =$C$17*(1+Underlying_Assets!H11) -> 85.525371 | D20: =$D$17*(1+Underlying_Assets!I11) -> 144.4201 | E20: =(LN(C20/Option_Portfolio!$E$4)+(Option_Portfolio!$H$4+0.5*Option_Portfolio!$G$4^2)*Option_Portfolio!$F$4)/(Option_Portfolio!$G$4*SQRT(Option_Portfolio!$F$4)) -> 0.15295811 | F20: =(LN(D20/Option_Portfolio!$E$5)+(Option_Portfolio!$H$5+0.5*Option_Portfolio!$G$5^2)*Option_Portfolio!$F$5)/(Option_Portfolio!$G$5*SQRT(Option_Portfolio!$F$5)) -> 1.3006566 | G20: =E20-Option_Portfolio!$G$4*SQRT(Option_Portfolio!$F$4) -> 0.032749959 | H20: =F20-Option_Portfolio!$G$5*SQRT(Option_Portfolio!$F$5) -> 1.1450931 | I20: =_xlfn.NORM.S.DIST(E20,TRUE) -> 0.56078435 | J20: =_xlfn.NORM.S.DIST(F20,TRUE) -> 0.90331198 | K20: =_xlfn.NORM.S.DIST(G20,TRUE) -> 0.51306301 | L20: =_xlfn.NORM.S.DIST(H20,TRUE) -> 0.8739147 | M20: =(1-K20)*Option_Portfolio!$E$4*EXP(-Option_Portfolio!$H$4*Option_Portfolio!$F$4)-(1-I20)*C20 -> 3.6191308 | N20: =J20*D20-L20*Option_Portfolio!$E$5*EXP(-Option_Portfolio!$H$5*Option_Portfolio!$F$5) -> 26.109684 | O20: =M20 * -Option_Portfolio!$B$4 * 1000 + N20 * Option_Portfolio!$B$5 * 1000 -> 26885452 | P20: =(O20/O19)-1 -> -0.043690516
B21: T4 | C21: =$C$17*(1+Underlying_Assets!H12) -> 85.266631 | D21: =$D$17*(1+Underlying_Assets!I12) -> 144.5949 | E21: =(LN(C21/Option_Portfolio!$E$4)+(Option_Portfolio!$H$4+0.5*Option_Portfolio!$G$4^2)*Option_Portfolio!$F$4)/(Option_Portfolio!$G$4*SQRT(Option_Portfolio!$F$4)) -> 0.1277528 | F21: =(LN(D21/Option_Portfolio!$E$5)+(Option_Portfolio!$H$5+0.5*Option_Portfolio!$G$5^2)*Option_Portfolio!$F$5)/(Option_Portfolio!$G$5*SQRT(Option_Portfolio!$F$5)) -> 1.3084323 | G21: =E21-Option_Portfolio!$G$4*SQRT(Option_Portfolio!$F$4) -> 0.0075446465 | H21: =F21-Option_Portfolio!$G$5*SQRT(Option_Portfolio!$F$5) -> 1.1528688 | I21: =_xlfn.NORM.S.DIST(E21,TRUE) -> 0.5508277 | J21: =_xlfn.NORM.S.DIST(F21,TRUE) -> 0.90463664 | K21: =_xlfn.NORM.S.DIST(G21,TRUE) -> 0.50300985 | L21: =_xlfn.NORM.S.DIST(H21,TRUE) -> 0.87551789 | M21: =(1-K21)*Option_Portfolio!$E$4*EXP(-Option_Portfolio!$H$4*Option_Portfolio!$F$4)-(1-I21)*C21 -> 3.7340601 | N21: =J21*D21-L21*Option_Portfolio!$E$5*EXP(-Option_Portfolio!$H$5*Option_Portfolio!$F$5) -> 26.267699 | O21: =M21 * -Option_Portfolio!$B$4 * 1000 + N21 * Option_Portfolio!$B$5 * 1000 -> 26396977 | P21: =(O21/O20)-1 -> -0.018168746
B22: T5 | C22: =$C$17*(1+Underlying_Assets!H13) -> 86.466977 | D22: =$D$17*(1+Underlying_Assets!I13) -> 144.3012 | E22: =(LN(C22/Option_Portfolio!$E$4)+(Option_Portfolio!$H$4+0.5*Option_Portfolio!$G$4^2)*Option_Portfolio!$F$4)/(Option_Portfolio!$G$4*SQRT(Option_Portfolio!$F$4)) -> 0.24404596 | F22: =(LN(D22/Option_Portfolio!$E$5)+(Option_Portfolio!$H$5+0.5*Option_Portfolio!$G$5^2)*Option_Portfolio!$F$5)/(Option_Portfolio!$G$5*SQRT(Option_Portfolio!$F$5)) -> 1.2953618 | G22: =E22-Option_Portfolio!$G$4*SQRT(Option_Portfolio!$F$4) -> 0.12383781 | H22: =F22-Option_Portfolio!$G$5*SQRT(Option_Portfolio!$F$5) -> 1.1397983 | I22: =_xlfn.NORM.S.DIST(E22,TRUE) -> 0.59640239 | J22: =_xlfn.NORM.S.DIST(F22,TRUE) -> 0.90240228 | K22: =_xlfn.NORM.S.DIST(G22,TRUE) -> 0.54927815 | L22: =_xlfn.NORM.S.DIST(H22,TRUE) -> 0.87281483 | M22: =(1-K22)*Option_Portfolio!$E$4*EXP(-Option_Portfolio!$H$4*Option_Portfolio!$F$4)-(1-I22)*C22 -> 3.222413 | N22: =J22*D22-L22*Option_Portfolio!$E$5*EXP(-Option_Portfolio!$H$5*Option_Portfolio!$F$5) -> 26.002329 | O22: =M22 * -Option_Portfolio!$B$4 * 1000 + N22 * Option_Portfolio!$B$5 * 1000 -> 29447768 | P22: =(O22/O21)-1 -> 0.11557348
B23: T6 | C23: =$C$17*(1+Underlying_Assets!H14) -> 85.285169 | D23: =$D$17*(1+Underlying_Assets!I14) -> 144.21114 | E23: =(LN(C23/Option_Portfolio!$E$4)+(Option_Portfolio!$H$4+0.5*Option_Portfolio!$G$4^2)*Option_Portfolio!$F$4)/(Option_Portfolio!$G$4*SQRT(Option_Portfolio!$F$4)) -> 0.12956118 | F23: =(LN(D23/Option_Portfolio!$E$5)+(Option_Portfolio!$H$5+0.5*Option_Portfolio!$G$5^2)*Option_Portfolio!$F$5)/(Option_Portfolio!$G$5*SQRT(Option_Portfolio!$F$5)) -> 1.291349 | G23: =E23-Option_Portfolio!$G$4*SQRT(Option_Portfolio!$F$4) -> 0.0093530271 | H23: =F23-Option_Portfolio!$G$5*SQRT(Option_Portfolio!$F$5) -> 1.1357855 | I23: =_xlfn.NORM.S.DIST(E23,TRUE) -> 0.55154319 | J23: =_xlfn.NORM.S.DIST(F23,TRUE) -> 0.90170865 | K23: =_xlfn.NORM.S.DIST(G23,TRUE) -> 0.50373126 | L23: =_xlfn.NORM.S.DIST(H23,TRUE) -> 0.87197682 | M23: =(1-K23)*Option_Portfolio!$E$4*EXP(-Option_Portfolio!$H$4*Option_Portfolio!$F$4)-(1-I23)*C23 -> 3.7257402 | N23: =J23*D23-L23*Option_Portfolio!$E$5*EXP(-Option_Portfolio!$H$5*Option_Portfolio!$F$5) -> 25.921097 | O23: =M23 * -Option_Portfolio!$B$4 * 1000 + N23 * Option_Portfolio!$B$5 * 1000 -> 25762012 | P23: =(O23/O22)-1 -> -0.12516248
B24: T7 | C24: =$C$17*(1+Underlying_Assets!H15) -> 85.32588 | D24: =$D$17*(1+Underlying_Assets!I15) -> 146.63291 | E24: =(LN(C24/Option_Portfolio!$E$4)+(Option_Portfolio!$H$4+0.5*Option_Portfolio!$G$4^2)*Option_Portfolio!$F$4)/(Option_Portfolio!$G$4*SQRT(Option_Portfolio!$F$4)) -> 0.13353135 | F24: =(LN(D24/Option_Portfolio!$E$5)+(Option_Portfolio!$H$5+0.5*Option_Portfolio!$G$5^2)*Option_Portfolio!$F$5)/(Option_Portfolio!$G$5*SQRT(Option_Portfolio!$F$5)) -> 1.3984034 | G24: =E24-Option_Portfolio!$G$4*SQRT(Option_Portfolio!$F$4) -> 0.013323199 | H24: =F24-Option_Portfolio!$G$5*SQRT(Option_Portfolio!$F$5) -> 1.2428399 | I24: =_xlfn.NORM.S.DIST(E24,TRUE) -> 0.55311341 | J24: =_xlfn.NORM.S.DIST(F24,TRUE) -> 0.91900402 | K24: =_xlfn.NORM.S.DIST(G24,TRUE) -> 0.50531503 | L24: =_xlfn.NORM.S.DIST(H24,TRUE) -> 0.89303659 | M24: =(1-K24)*Option_Portfolio!$E$4*EXP(-Option_Portfolio!$H$4*Option_Portfolio!$F$4)-(1-I24)*C24 -> 3.7075147 | N24: =J24*D24-L24*Option_Portfolio!$E$5*EXP(-Option_Portfolio!$H$5*Option_Portfolio!$F$5) -> 28.126329 | O24: =M24 * -Option_Portfolio!$B$4 * 1000 + N24 * Option_Portfolio!$B$5 * 1000 -> 30300056 | P24: =(O24/O23)-1 -> 0.17615255
B25: T8 | C25: =$C$17*(1+Underlying_Assets!H16) -> 86.173468 | D25: =$D$17*(1+Underlying_Assets!I16) -> 144.65403 | E25: =(LN(C25/Option_Portfolio!$E$4)+(Option_Portfolio!$H$4+0.5*Option_Portfolio!$G$4^2)*Option_Portfolio!$F$4)/(Option_Portfolio!$G$4*SQRT(Option_Portfolio!$F$4)) -> 0.21575974 | F25: =(LN(D25/Option_Portfolio!$E$5)+(Option_Portfolio!$H$5+0.5*Option_Portfolio!$G$5^2)*Option_Portfolio!$F$5)/(Option_Portfolio!$G$5*SQRT(Option_Portfolio!$F$5)) -> 1.3110606 | G25: =E25-Option_Portfolio!$G$4*SQRT(Option_Portfolio!$F$4) -> 0.095551587 | H25: =F25-Option_Portfolio!$G$5*SQRT(Option_Portfolio!$F$5) -> 1.1554971 | I25: =_xlfn.NORM.S.DIST(E25,TRUE) -> 0.58541248 | J25: =_xlfn.NORM.S.DIST(F25,TRUE) -> 0.90508135 | K25: =_xlfn.NORM.S.DIST(G25,TRUE) -> 0.53806164 | L25: =_xlfn.NORM.S.DIST(H25,TRUE) -> 0.87605654 | M25: =(1-K25)*Option_Portfolio!$E$4*EXP(-Option_Portfolio!$H$4*Option_Portfolio!$F$4)-(1-I25)*C25 -> 3.3424826 | N25: =J25*D25-L25*Option_Portfolio!$E$5*EXP(-Option_Portfolio!$H$5*Option_Portfolio!$F$5) -> 26.321204 | O25: =M25 * -Option_Portfolio!$B$4 * 1000 + N25 * Option_Portfolio!$B$5 * 1000 -> 29245031 | P25: =(O25/O24)-1 -> -0.034819247
B26: T9 | C26: =$C$17*(1+Underlying_Assets!H17) -> 85.912515 | D26: =$D$17*(1+Underlying_Assets!I17) -> 144.85845 | E26: =(LN(C26/Option_Portfolio!$E$4)+(Option_Portfolio!$H$4+0.5*Option_Portfolio!$G$4^2)*Option_Portfolio!$F$4)/(Option_Portfolio!$G$4*SQRT(Option_Portfolio!$F$4)) -> 0.19052997 | F26: =(LN(D26/Option_Portfolio!$E$5)+(Option_Portfolio!$H$5+0.5*Option_Portfolio!$G$5^2)*Option_Portfolio!$F$5)/(Option_Portfolio!$G$5*SQRT(Option_Portfolio!$F$5)) -> 1.3201381 | G26: =E26-Option_Portfolio!$G$4*SQRT(Option_Portfolio!$F$4) -> 0.070321816 | H26: =F26-Option_Portfolio!$G$5*SQRT(Option_Portfolio!$F$5) -> 1.1645746 | I26: =_xlfn.NORM.S.DIST(E26,TRUE) -> 0.57555307 | J26: =_xlfn.NORM.S.DIST(F26,TRUE) -> 0.90660554 | K26: =_xlfn.NORM.S.DIST(G26,TRUE) -> 0.52803124 | L26: =_xlfn.NORM.S.DIST(H26,TRUE) -> 0.87790438 | M26: =(1-K26)*Option_Portfolio!$E$4*EXP(-Option_Portfolio!$H$4*Option_Portfolio!$F$4)-(1-I26)*C26 -> 3.4519551 | N26: =J26*D26-L26*Option_Portfolio!$E$5*EXP(-Option_Portfolio!$H$5*Option_Portfolio!$F$5) -> 26.506372 | O26: =M26 * -Option_Portfolio!$B$4 * 1000 + N26 * Option_Portfolio!$B$5 * 1000 -> 28849058 | P26: =(O26/O25)-1 -> -0.013539854
B27: T10 | C27: =$C$17*(1+Underlying_Assets!H18) -> 84.904982 | D27: =$D$17*(1+Underlying_Assets!I18) -> 144.68316 | E27: =(LN(C27/Option_Portfolio!$E$4)+(Option_Portfolio!$H$4+0.5*Option_Portfolio!$G$4^2)*Option_Portfolio!$F$4)/(Option_Portfolio!$G$4*SQRT(Option_Portfolio!$F$4)) -> 0.092394025 | F27: =(LN(D27/Option_Portfolio!$E$5)+(Option_Portfolio!$H$5+0.5*Option_Portfolio!$G$5^2)*Option_Portfolio!$F$5)/(Option_Portfolio!$G$5*SQRT(Option_Portfolio!$F$5)) -> 1.3123546 | G27: =E27-Option_Portfolio!$G$4*SQRT(Option_Portfolio!$F$4) -> -0.027814128 | H27: =F27-Option_Portfolio!$G$5*SQRT(Option_Portfolio!$F$5) -> 1.1567912 | I27: =_xlfn.NORM.S.DIST(E27,TRUE) -> 0.53680751 | J27: =_xlfn.NORM.S.DIST(F27,TRUE) -> 0.90529975 | K27: =_xlfn.NORM.S.DIST(G27,TRUE) -> 0.4889052 | L27: =_xlfn.NORM.S.DIST(H27,TRUE) -> 0.87632115 | M27: =(1-K27)*Option_Portfolio!$E$4*EXP(-Option_Portfolio!$H$4*Option_Portfolio!$F$4)-(1-I27)*C27 -> 3.8990347 | N27: =J27*D27-L27*Option_Portfolio!$E$5*EXP(-Option_Portfolio!$H$5*Option_Portfolio!$F$5) -> 26.347566 | O27: =M27 * -Option_Portfolio!$B$4 * 1000 + N27 * Option_Portfolio!$B$5 * 1000 -> 25401890 | P27: =(O27/O26)-1 -> -0.11948979
B28: T11 | C28: =$C$17*(1+Underlying_Assets!H19) -> 86.052951 | D28: =$D$17*(1+Underlying_Assets!I19) -> 146.1448 | E28: =(LN(C28/Option_Portfolio!$E$4)+(Option_Portfolio!$H$4+0.5*Option_Portfolio!$G$4^2)*Option_Portfolio!$F$4)/(Option_Portfolio!$G$4*SQRT(Option_Portfolio!$F$4)) -> 0.20411731 | F28: =(LN(D28/Option_Portfolio!$E$5)+(Option_Portfolio!$H$5+0.5*Option_Portfolio!$G$5^2)*Option_Portfolio!$F$5)/(Option_Portfolio!$G$5*SQRT(Option_Portfolio!$F$5)) -> 1.3769695 | G28: =E28-Option_Portfolio!$G$4*SQRT(Option_Portfolio!$F$4) -> 0.083909156 | H28: =F28-Option_Portfolio!$G$5*SQRT(Option_Portfolio!$F$5) -> 1.221406 | I28: =_xlfn.NORM.S.DIST(E28,TRUE) -> 0.58086909 | J28: =_xlfn.NORM.S.DIST(F28,TRUE) -> 0.91573915 | K28: =_xlfn.NORM.S.DIST(G28,TRUE) -> 0.53343567 | L28: =_xlfn.NORM.S.DIST(H28,TRUE) -> 0.88903382 | M28: =(1-K28)*Option_Portfolio!$E$4*EXP(-Option_Portfolio!$H$4*Option_Portfolio!$F$4)-(1-I28)*C28 -> 3.3927209 | N28: =J28*D28-L28*Option_Portfolio!$E$5*EXP(-Option_Portfolio!$H$5*Option_Portfolio!$F$5) -> 27.678547 | O28: =M28 * -Option_Portfolio!$B$4 * 1000 + N28 * Option_Portfolio!$B$5 * 1000 -> 31608047 | P28: =(O28/O27)-1 -> 0.24431872
B29: T12 | C29: =$C$17*(1+Underlying_Assets!H20) -> 85.133696 | D29: =$D$17*(1+Underlying_Assets!I20) -> 146.20484 | E29: =(LN(C29/Option_Portfolio!$E$4)+(Option_Portfolio!$H$4+0.5*Option_Portfolio!$G$4^2)*Option_Portfolio!$F$4)/(Option_Portfolio!$G$4*SQRT(Option_Portfolio!$F$4)) -> 0.1147731 | F29: =(LN(D29/Option_Portfolio!$E$5)+(Option_Portfolio!$H$5+0.5*Option_Portfolio!$G$5^2)*Option_Portfolio!$F$5)/(Option_Portfolio!$G$5*SQRT(Option_Portfolio!$F$5)) -> 1.3796098 | G29: =E29-Option_Portfolio!$G$4*SQRT(Option_Portfolio!$F$4) -> -0.0054350529 | H29: =F29-Option_Portfolio!$G$5*SQRT(Option_Portfolio!$F$5) -> 1.2240463 | I29: =_xlfn.NORM.S.DIST(E29,TRUE) -> 0.54568751 | J29: =_xlfn.NORM.S.DIST(F29,TRUE) -> 0.91614659 | K29: =_xlfn.NORM.S.DIST(G29,TRUE) -> 0.49783174 | L29: =_xlfn.NORM.S.DIST(H29,TRUE) -> 0.88953262 | M29: =(1-K29)*Option_Portfolio!$E$4*EXP(-Option_Portfolio!$H$4*Option_Portfolio!$F$4)-(1-I29)*C29 -> 3.7941122 | N29: =J29*D29-L29*Option_Portfolio!$E$5*EXP(-Option_Portfolio!$H$5*Option_Portfolio!$F$5) -> 27.73354 | O29: =M29 * -Option_Portfolio!$B$4 * 1000 + N29 * Option_Portfolio!$B$5 * 1000 -> 28908294 | P29: =(O29/O28)-1 -> -0.085413474
... B267: T250 | C267: =$C$17*(1+Underlying_Assets!H258) -> 85.783424 | D267: =$D$17*(1+Underlying_Assets!I258) -> 149.93866 | E267: =(LN(C267/Option_Portfolio!$E$4)+(Option_Portfolio!$H$4+0.5*Option_Portfolio!$G$4^2)*Option_Portfolio!$F$4)/(Option_Portfolio!$G$4*SQRT(Option_Portfolio!$F$4)) -> 0.17802065 | F267: =(LN(D267/Option_Portfolio!$E$5)+(Option_Portfolio!$H$5+0.5*Option_Portfolio!$G$5^2)*Option_Portfolio!$F$5)/(Option_Portfolio!$G$5*SQRT(Option_Portfolio!$F$5)) -> 1.5417146 | G267: =E267-Option_Portfolio!$G$4*SQRT(Option_Portfolio!$F$4) -> 0.0578125 | H267: =F267-Option_Portfolio!$G$5*SQRT(Option_Portfolio!$F$5) -> 1.3861511 | I267: =_xlfn.NORM.S.DIST(E267,TRUE) -> 0.57064662 | J267: =_xlfn.NORM.S.DIST(F267,TRUE) -> 0.93842852 | K267: =_xlfn.NORM.S.DIST(G267,TRUE) -> 0.52305101 | L267: =_xlfn.NORM.S.DIST(H267,TRUE) -> 0.91714962 | M267: =(1-K267)*Option_Portfolio!$E$4*EXP(-Option_Portfolio!$H$4*Option_Portfolio!$F$4)-(1-I267)*C267 -> 3.5070641 | N267: =J267*D267-L267*Option_Portfolio!$E$5*EXP(-Option_Portfolio!$H$5*Option_Portfolio!$F$5) -> 31.197674 | O267: =M267 * -Option_Portfolio!$B$4 * 1000 + N267 * Option_Portfolio!$B$5 * 1000 -> 37845899 | P267: =(O267/O266)-1 -> 0.63435919

Sheet Fixed Income VaR
C2: FIXED INCOME PORTFOLIO | H2: 1
H3: π : | I3: =SUM(E10:E12) -> 4.2985939e+08
C4: bonds | D4: maturity in years | E4: annual coupon | L4: Insights
B5: A | C5: 2000000 | D5: 1 | E5: zero | F5: 0 | H5: 2 | L5: The fixed-income portfolio, primarily composed of USD-denominated government bonds, shows a 1-day VaR(99%) between $2.27M and $2.42M,
B6: B | C6: -1500000 | D6: 3 | E6: 5 | F6: 5 | H6: σ | I6: {=SQRT(MMULT(MMULT(C26:G26,_xlfn.ANCHORARRAY(C43)),TRANSPOSE(C26:G26)))} -> 978748.46 | L6: with the expected shortfall ranging from $2.61M to $5.45M, depending on the risk assessment method.
B7: C | C7: 4000000 | D7: 5 | E7: 2 | F7: 2 | H7: VaR(99%,1) | I7: =_xlfn.NORM.S.INV(0.99)*I6 -> 2276909.4 | L7: The historical simulation approach reveals slightly higher tail risk than the variance-covariance method, suggesting sensitivity to nonlinearities in yield changes.
H8: ES(99%,1) | I8: =I6*EXP(-(_xlfn.NORM.S.INV(0.99)^2)/2)/(SQRT(2*PI())*0.01) -> 2608574.3 | L8: The portfolio remains exposed mainly at the 5-year maturity due to concentration, indicating moderate risk under normal conditions,
C9: bond | D9: price | E9: value | L9: but significant potential losses under stress scenarios.
C10: 2000000 | D10: =100/(1+(TSIR!B1080/100)) -> 96.200096 | E10: =C10*D10 -> 1.9240019e+08 | H10: 3
C11: -1500000 | D11: =(F6/(1+(TSIR!D1080/100))) + (F6/(1+(TSIR!D1080/100))^2) + (F6+100/(1+(TSIR!D1080/100))^3) -> 103.98095 | E11: =C11*D11 -> -1.5597143e+08 | H11: 1st percentile Return : | I11: =_xlfn.PERCENTILE.INC(T17:T267,0.01) -> -0.0059874944
C12: 4000000 | D12: =(F7/(1+(TSIR!F1080/100)))+(F7/(1+(TSIR!F1080/100))^2)+(F7+100/(1+(TSIR!F1080/100))^3)+(F7/(1+(TSIR!F1080/100))^4)+(F7/(1+(TSIR!F1080/100))^5) -> 98.357655 | E12: =C12*D12 -> 3.9343062e+08 | H12: VaR(99%,1) : | I12: =ABS(S17*I11) -> 2416696.8
H13: Mean Below VaR : | I13: =AVERAGEIF(T17:T267,"<-0.0124") -> -0.013494974
H14: ES(99%,1) : | I14: =ABS(S17*I13) -> 5446896.1
M15: Years maturity | Q15: Price | S15: π | T15: π return
B16: T | C16: 1 | D16: 2 | E16: 3 | F16: 4 | G16: 5 | J16: date | K16: 1 | L16: 2 | M16: 3 | N16: 4 | O16: 5
B17: yT | C17: =TSIR!B1080 -> 3.95 | D17: =TSIR!C1080 -> 3.74 | E17: =TSIR!D1080 -> 3.76 | F17: =TSIR!E1080 -> 3.7865 | G17: =TSIR!F1080 -> 3.88 | J17: 45772 | K17: =TSIR!B1080 -> 3.95 | L17: =TSIR!C1080 -> 3.74 | M17: =TSIR!D1080 -> 3.76 | N17: =TSIR!E1080 -> 3.7865 | O17: =TSIR!F1080 -> 3.88 | P17: =100/(1+(K17/100)) -> 96.200096 | Q17: =$F$6 * ((1 - (1 + M17 / 100)^(-$D$6)) / (M17 / 100)) + 100 / (1 + M17 / 100)^$D$6 -> 103.45685 | R17: =$F$7*((1-(1+O17/100)^(-$D$7))/(O17/100)) + (100/(1+O17/100)^$D$7) -> 91.602285 | S17: =P17*$C$10+Q17*$C$11+R17*$C$12 -> 4.0362406e+08 | T17: 0
B18: MD | C18: =C16/(1+(C17/100)) -> 0.96200096 | D18: =D16/(1+(D17/100)) -> 1.9278967 | E18: =E16/(1+(E17/100)) -> 2.8912876 | F18: =F16/(1+(F17/100)) -> 3.8540658 | G18: =G16/(1+(G17/100)) -> 4.8132461 | J18: T1 | K18: =K17*((TSIR!B4/TSIR!B3)) -> 4.345 | L18: =L17*((TSIR!C4/TSIR!C3)) -> 4.0276923 | M18: =M17*((TSIR!D4/TSIR!D3)) -> 4.4235294 | N18: =N17*((TSIR!E4/TSIR!E3)) -> 4.3348446 | O18: =O17*((TSIR!F4/TSIR!F3)) -> 4.3905263 | P18: =100/(1+(K18/100)) -> 95.835929 | Q18: =$F$6 * ((1 - (1 + M18 / 100)^(-$D$6)) / ($M$17 / 100)) + 100 / (1 + M18 / 100)^$D$6 -> 104.01604 | R18: =$F$7*((1-(1+O18/100)^(-$D$7))/($O$17/100)) + (100/(1+O18/100)^$D$7) -> 90.632343 | S18: =P18*$C$10+Q18*$C$11+R18*$C$12 -> 3.9817716e+08 | T18: =(S18/S17)-1 -> -0.013494974
B19: σ | C19: =STDEV(TSIR!G831:G1080) -> 0.00044750374 | D19: =STDEV(TSIR!H831:H1080) -> 0.00059178106 | E19: =STDEV(TSIR!I831:I1080) -> 0.00060028052 | F19: =STDEV(TSIR!J831:J1080) -> 0.00048602164 | G19: =STDEV(TSIR!K831:K1080) -> 0.00060628886 | J19: T2 | K19: =K18*((TSIR!B5/TSIR!B4)) -> 4.345 | L19: =L18*((TSIR!C5/TSIR!C4)) -> 4.0276923 | M19: =M18*((TSIR!D5/TSIR!D4)) -> 4.8658824 | N19: =N18*((TSIR!E5/TSIR!E4)) -> 4.675673 | O19: =O18*((TSIR!F5/TSIR!F4)) -> 4.6968421 | P19: =100/(1+(K19/100)) -> 95.835929 | Q19: =$F$6*((1-(1+M19/100)^(-$D$6))/(M19/100))+($F$6+100)/(1+$M$17/100)^$D$6 -> 107.64438 | R19: =$F$7*((1-(1+O19/100)^(-$D$7))/(O19/100))+($F$7+100)/(1+$O$17/100)^$D$7 -> 93.053917 | S19: =P19*$C$10+Q19*$C$11+R19*$C$12 -> 4.0242096e+08 | T19: =(S19/S18)-1 -> 0.010658065
B20: V | C20: =C18*C19 -> 0.00043049903 | D20: =D18*D19 -> 0.0011408927 | E20: =E18*E19 -> 0.0017355836 | F20: =F18*F19 -> 0.0018731594 | G20: =G18*G19 -> 0.0029182175 | J20: T3 | K20: =K19*((TSIR!B6/TSIR!B5)) -> 3.95 | L20: =L19*((TSIR!C6/TSIR!C5)) -> 4.0276923 | M20: =M19*((TSIR!D6/TSIR!D5)) -> 5.3082353 | N20: =N19*((TSIR!E6/TSIR!E5)) -> 5.023772 | O20: =O19*((TSIR!F6/TSIR!F5)) -> 5.0031579 | P20: =100/(1+(K20/100)) -> 96.200096 | Q20: =$F$6*((1-(1+M20/100)^(-$D$6))/(M20/100))+($F$6+100)/(1+$M$17/100)^$D$6 -> 107.53182 | R20: =$F$7*((1-(1+O20/100)^(-$D$7))/(O20/100))+($F$7+100)/(1+$O$17/100)^$D$7 -> 92.980114 | S20: =P20*$C$10+Q20*$C$11+R20*$C$12 -> 4.0302292e+08 | T20: =(S20/S19)-1 -> 0.0014958313
B21: Pos A | C21: =C5*100 -> 200000000 | D21: 0 | E21: 0 | F21: 0 | G21: 0 | J21: T4 | K21: =K20*((TSIR!B7/TSIR!B6)) -> 3.95 | L21: =L20*((TSIR!C7/TSIR!C6)) -> 4.0276923 | M21: =M20*((TSIR!D7/TSIR!D6)) -> 4.8658824 | N21: =N20*((TSIR!E7/TSIR!E6)) -> 4.9564139 | O21: =O20*((TSIR!F7/TSIR!F6)) -> 5.1052632 | P21: =100/(1+(K21/100)) -> 96.200096 | Q21: =$F$6*((1-(1+M21/100)^(-$D$6))/(M21/100))+($F$6+100)/(1+$M$17/100)^$D$6 -> 107.64438 | R21: =$F$7*((1-(1+O21/100)^(-$D$7))/(O21/100))+($F$7+100)/(1+$O$17/100)^$D$7 -> 92.955732 | S21: =P21*$C$10+Q21*$C$11+R21*$C$12 -> 4.0275656e+08 | T21: =(S21/S20)-1 -> -0.00066090631
B22: Pos B | C22: =C6*F6 -> -7500000 | D22: =C6*F6 -> -7500000 | E22: =C6*F6+C6*100 -> -157500000 | F22: 0 | G22: 0 | J22: T5 | K22: =K21*((TSIR!B8/TSIR!B7)) -> 4.345 | L22: =L21*((TSIR!C8/TSIR!C7)) -> 4.0276923 | M22: =M21*((TSIR!D8/TSIR!D7)) -> 5.0870588 | N22: =N21*((TSIR!E8/TSIR!E7)) -> 5.0248847 | O22: =O21*((TSIR!F8/TSIR!F7)) -> 5.1052632 | P22: =100/(1+(K22/100)) -> 95.835929 | Q22: =$F$6*((1-(1+M22/100)^(-$D$6))/(M22/100))+($F$6+100)/(1+$M$17/100)^$D$6 -> 107.5879 | R22: =$F$7*((1-(1+O22/100)^(-$D$7))/(O22/100))+($F$7+100)/(1+$O$17/100)^$D$7 -> 92.955732 | S22: =P22*$C$10+Q22*$C$11+R22*$C$12 -> 4.0211293e+08 | T22: =(S22/S21)-1 -> -0.0015980497
B23: Pos C | C23: =C7*F7 -> 8000000 | D23: =C7*F7 -> 8000000 | E23: =C7*F7 -> 8000000 | F23: =C7*F7 -> 8000000 | G23: =IF(D7=5, C7*F7 + C7*100, C7*F7) -> 408000000 | J23: T6 | K23: =K22*((TSIR!B9/TSIR!B8)) -> 4.74 | L23: =L22*((TSIR!C9/TSIR!C8)) -> 4.0276923 | M23: =M22*((TSIR!D9/TSIR!D8)) -> 4.8658824 | N23: =N22*((TSIR!E9/TSIR!E8)) -> 4.8144116 | O23: =O22*((TSIR!F9/TSIR!F8)) -> 4.9010526 | P23: =100/(1+(K23/100)) -> 95.474508 | Q23: =$F$6*((1-(1+M23/100)^(-$D$6))/(M23/100))+($F$6+100)/(1+$M$17/100)^$D$6 -> 107.64438 | R23: =$F$7*((1-(1+O23/100)^(-$D$7))/(O23/100))+($F$7+100)/(1+$O$17/100)^$D$7 -> 93.004605 | S23: =P23*$C$10+Q23*$C$11+R23*$C$12 -> 4.0150087e+08 | T23: =(S23/S22)-1 -> -0.001522104
B24: πZCB | C24: =SUM(C21:C23) -> 200500000 | D24: =SUM(D21:D23) -> 500000 | E24: =SUM(E21:E23) -> -149500000 | F24: =SUM(F21:F23) -> 8000000 | G24: =SUM(G21:G23) -> 408000000 | J24: T7 | K24: =K23*((TSIR!B10/TSIR!B9)) -> 3.95 | L24: =L23*((TSIR!C10/TSIR!C9)) -> 4.6030769 | M24: =M23*((TSIR!D10/TSIR!D9)) -> 5.0870588 | N24: =N23*((TSIR!E10/TSIR!E9)) -> 4.956521 | O24: =O23*((TSIR!F10/TSIR!F9)) -> 5.0031579 | P24: =100/(1+(K24/100)) -> 96.200096 | Q24: =$F$6*((1-(1+M24/100)^(-$D$6))/(M24/100))+($F$6+100)/(1+$M$17/100)^$D$6 -> 107.5879 | R24: =$F$7*((1-(1+O24/100)^(-$D$7))/(O24/100))+($F$7+100)/(1+$O$17/100)^$D$7 -> 92.980114 | S24: =P24*$C$10+Q24*$C$11+R24*$C$12 -> 4.0293879e+08 | T24: =(S24/S23)-1 -> 0.003581364
B25: DF | C25: =1/(1+(C18/100))^C17 -> 0.96288872 | D25: =1/(1+(D18/100))^D17 -> 0.93107346 | E25: =1/(1+(E18/100))^E17 -> 0.89837251 | F25: =1/(1+(F18/100))^F17 -> 0.86658747 | G25: =1/(1+(G18/100))^G17 -> 0.83326906 | J25: T8 | K25: =K24*((TSIR!B11/TSIR!B10)) -> 3.95 | L25: =L24*((TSIR!C11/TSIR!C10)) -> 3.74 | M25: =M24*((TSIR!D11/TSIR!D10)) -> 4.4235294 | N25: =N24*((TSIR!E11/TSIR!E10)) -> 4.5411249 | O25: =O24*((TSIR!F11/TSIR!F10)) -> 4.6968421 | P25: =100/(1+(K25/100)) -> 96.200096 | Q25: =$F$6*((1-(1+M25/100)^(-$D$6))/(M25/100))+($F$6+100)/(1+$M$17/100)^$D$6 -> 107.75851 | R25: =$F$7*((1-(1+O25/100)^(-$D$7))/(O25/100))+($F$7+100)/(1+$O$17/100)^$D$7 -> 93.053917 | S25: =P25*$C$10+Q25*$C$11+R25*$C$12 -> 4.0297809e+08 | T25: =(S25/S24)-1 -> 9.7532673e-05
B26: x | C26: =C24*C25 -> 1.9305919e+08 | D26: =D24*D25 -> 465536.73 | E26: =E24*E25 -> -1.3430669e+08 | F26: =F24*F25 -> 6932699.7 | G26: =G24*G25 -> 3.3997378e+08 | J26: T9 | K26: =K25*((TSIR!B12/TSIR!B11)) -> 3.95 | L26: =L25*((TSIR!C12/TSIR!C11)) -> 4.0276923 | M26: =M25*((TSIR!D12/TSIR!D11)) -> 4.6447059 | N26: =N25*((TSIR!E12/TSIR!E11)) -> 4.5413851 | O26: =O25*((TSIR!F12/TSIR!F11)) -> 4.5947368 | P26: =100/(1+(K26/100)) -> 96.200096 | Q26: =$F$6*((1-(1+M26/100)^(-$D$6))/(M26/100))+($F$6+100)/(1+$M$17/100)^$D$6 -> 107.70124 | R26: =$F$7*((1-(1+O26/100)^(-$D$7))/(O26/100))+($F$7+100)/(1+$O$17/100)^$D$7 -> 93.078739 | S26: =P26*$C$10+Q26*$C$11+R26*$C$12 -> 4.0316328e+08 | T26: =(S26/S25)-1 -> 0.00045955224
J27: T10 | K27: =K26*((TSIR!B13/TSIR!B12)) -> 3.95 | L27: =L26*((TSIR!C13/TSIR!C12)) -> 3.74 | M27: =M26*((TSIR!D13/TSIR!D12)) -> 4.2023529 | N27: =N26*((TSIR!E13/TSIR!E12)) -> 4.404017 | O27: =O26*((TSIR!F13/TSIR!F12)) -> 4.5947368 | P27: =100/(1+(K27/100)) -> 96.200096 | Q27: =$F$6*((1-(1+M27/100)^(-$D$6))/(M27/100))+($F$6+100)/(1+$M$17/100)^$D$6 -> 107.81618 | R27: =$F$7*((1-(1+O27/100)^(-$D$7))/(O27/100))+($F$7+100)/(1+$O$17/100)^$D$7 -> 93.078739 | S27: =P27*$C$10+Q27*$C$11+R27*$C$12 -> 4.0299088e+08 | T27: =(S27/S26)-1 -> -0.00042763336
B28: Vector V | C28: 1y | D28: 2y | E28: 3y | F28: 4y | G28: 5y | J28: T11 | K28: =K27*((TSIR!B14/TSIR!B13)) -> 3.95 | L28: =L27*((TSIR!C14/TSIR!C13)) -> 3.74 | M28: =M27*((TSIR!D14/TSIR!D13)) -> 4.2023529 | N28: =N27*((TSIR!E14/TSIR!E13)) -> 4.4061613 | O28: =O27*((TSIR!F14/TSIR!F13)) -> 4.5947368 | P28: =100/(1+(K28/100)) -> 96.200096 | Q28: =$F$6*((1-(1+M28/100)^(-$D$6))/(M28/100))+($F$6+100)/(1+$M$17/100)^$D$6 -> 107.81618 | R28: =$F$7*((1-(1+O28/100)^(-$D$7))/(O28/100))+($F$7+100)/(1+$O$17/100)^$D$7 -> 93.078739 | S28: =P28*$C$10+Q28*$C$11+R28*$C$12 -> 4.0299088e+08 | T28: =(S28/S27)-1 -> 0
B29: {=TRANSPOSE(C28:G28)} -> 1y | C29: =C20 -> 0.00043049903 | D29: 0 | E29: 0 | F29: 0 | G29: 0 | J29: T12 | K29: =K28*((TSIR!B15/TSIR!B14)) -> 3.95 | L29: =L28*((TSIR!C15/TSIR!C14)) -> 3.74 | M29: =M28*((TSIR!D15/TSIR!D14)) -> 4.2023529 | N29: =N28*((TSIR!E15/TSIR!E14)) -> 4.3383045 | O29: =O28*((TSIR!F15/TSIR!F14)) -> 4.4926316 | P29: =100/(1+(K29/100)) -> 96.200096 | Q29: =$F$6*((1-(1+M29/100)^(-$D$6))/(M29/100))+($F$6+100)/(1+$M$17/100)^$D$6 -> 107.81618 | R29: =$F$7*((1-(1+O29/100)^(-$D$7))/(O29/100))+($F$7+100)/(1+$O$17/100)^$D$7 -> 93.103673 | S29: =P29*$C$10+Q29*$C$11+R29*$C$12 -> 4.0309061e+08 | T29: =(S29/S28)-1 -> 0.00024748694
B30: 2y | C30: 0 | D30: =D20 -> 0.0011408927 | E30: 0 | F30: 0 | G30: 0 | J30: T13 | K30: =K29*((TSIR!B16/TSIR!B15)) -> 3.95 | L30: =L29*((TSIR!C16/TSIR!C15)) -> 3.74 | M30: =M29*((TSIR!D16/TSIR!D15)) -> 3.76 | N30: =N29*((TSIR!E16/TSIR!E15)) -> 4.060444 | O30: =O29*((TSIR!F16/TSIR!F15)) -> 4.2884211 | P30: =100/(1+(K30/100)) -> 96.200096 | Q30: =$F$6*((1-(1+M30/100)^(-$D$6))/(M30/100))+($F$6+100)/(1+$M$17/100)^$D$6 -> 107.93274 | R30: =$F$7*((1-(1+O30/100)^(-$D$7))/(O30/100))+($F$7+100)/(1+$O$17/100)^$D$7 -> 93.153878 | S30: =P30*$C$10+Q30*$C$11+R30*$C$12 -> 4.0311659e+08 | T30: =(S30/S29)-1 -> 6.4436543e-05
B31: 3y | C31: 0 | D31: 0 | E31: =E20 -> 0.0017355836 | F31: 0 | G31: 0 | J31: T14 | K31: =K30*((TSIR!B17/TSIR!B16)) -> 3.555 | L31: =L30*((TSIR!C17/TSIR!C16)) -> 3.1646154 | M31: =M30*((TSIR!D17/TSIR!D16)) -> 3.9811765 | N31: =N30*((TSIR!E17/TSIR!E16)) -> 4.1263933 | O31: =O30*((TSIR!F17/TSIR!F16)) -> 4.2884211 | P31: =100/(1+(K31/100)) -> 96.567042 | Q31: =$F$6*((1-(1+M31/100)^(-$D$6))/(M31/100))+($F$6+100)/(1+$M$17/100)^$D$6 -> 107.87426 | R31: =$F$7*((1-(1+O31/100)^(-$D$7))/(O31/100))+($F$7+100)/(1+$O$17/100)^$D$7 -> 93.153878 | S31: =P31*$C$10+Q31*$C$11+R31*$C$12 -> 4.0393821e+08 | T31: =(S31/S30)-1 -> 0.0020381741
B32: 4y | C32: 0 | D32: 0 | E32: 0 | F32: =F20 -> 0.0018731594 | G32: 0 | J32: T15 | K32: =K31*((TSIR!B18/TSIR!B17)) -> 3.555 | L32: =L31*((TSIR!C18/TSIR!C17)) -> 3.4523077 | M32: =M31*((TSIR!D18/TSIR!D17)) -> 3.9811765 | N32: =N31*((TSIR!E18/TSIR!E17)) -> 4.0587579 | O32: =O31*((TSIR!F18/TSIR!F17)) -> 4.1863158 | P32: =100/(1+(K32/100)) -> 96.567042 | Q32: =$F$6*((1-(1+M32/100)^(-$D$6))/(M32/100))+($F$6+100)/(1+$M$17/100)^$D$6 -> 107.87426 | R32: =$F$7*((1-(1+O32/100)^(-$D$7))/(O32/100))+($F$7+100)/(1+$O$17/100)^$D$7 -> 93.17915 | S32: =P32*$C$10+Q32*$C$11+R32*$C$12 -> 4.040393e+08 | T32: =(S32/S31)-1 -> 0.00025026096
B33: 5y | C33: 0 | D33: 0 | E33: 0 | F33: 0 | G33: =G20 -> 0.0029182175 | J33: T16 | K33: =K32*((TSIR!B19/TSIR!B18)) -> 3.16 | L33: =L32*((TSIR!C19/TSIR!C18)) -> 3.4523077 | M33: =M32*((TSIR!D19/TSIR!D18)) -> 3.9811765 | N33: =N32*((TSIR!E19/TSIR!E18)) -> 4.1289343 | O33: =O32*((TSIR!F19/TSIR!F18)) -> 4.2884211 | P33: =100/(1+(K33/100)) -> 96.936797 | Q33: =$F$6*((1-(1+M33/100)^(-$D$6))/(M33/100))+($F$6+100)/(1+$M$17/100)^$D$6 -> 107.87426 | R33: =$F$7*((1-(1+O33/100)^(-$D$7))/(O33/100))+($F$7+100)/(1+$O$17/100)^$D$7 -> 93.153878 | S33: =P33*$C$10+Q33*$C$11+R33*$C$12 -> 4.0467772e+08 | T33: =(S33/S32)-1 -> 0.0015800966
J34: T17 | K34: =K33*((TSIR!B20/TSIR!B19)) -> 3.95 | L34: =L33*((TSIR!C20/TSIR!C19)) -> 3.1646154 | M34: =M33*((TSIR!D20/TSIR!D19)) -> 4.2023529 | N34: =N33*((TSIR!E20/TSIR!E19)) -> 4.4059919 | O34: =O33*((TSIR!F20/TSIR!F19)) -> 4.5947368 | P34: =100/(1+(K34/100)) -> 96.200096 | Q34: =$F$6*((1-(1+M34/100)^(-$D$6))/(M34/100))+($F$6+100)/(1+$M$17/100)^$D$6 -> 107.81618 | R34: =$F$7*((1-(1+O34/100)^(-$D$7))/(O34/100))+($F$7+100)/(1+$O$17/100)^$D$7 -> 93.078739 | S34: =P34*$C$10+Q34*$C$11+R34*$C$12 -> 4.0299088e+08 | T34: =(S34/S33)-1 -> -0.004168358
B35: R_Changes | C35: 1y | D35: 2y | E35: 3y | F35: 4y | G35: 5y | J35: T18 | K35: =K34*((TSIR!B21/TSIR!B20)) -> 3.16 | L35: =L34*((TSIR!C21/TSIR!C20)) -> 3.1646154 | M35: =M34*((TSIR!D21/TSIR!D20)) -> 3.76 | N35: =N34*((TSIR!E21/TSIR!E20)) -> 4.0617227 | O35: =O34*((TSIR!F21/TSIR!F20)) -> 4.2884211 | P35: =100/(1+(K35/100)) -> 96.936797 | Q35: =$F$6*((1-(1+M35/100)^(-$D$6))/(M35/100))+($F$6+100)/(1+$M$17/100)^$D$6 -> 107.93274 | R35: =$F$7*((1-(1+O35/100)^(-$D$7))/(O35/100))+($F$7+100)/(1+$O$17/100)^$D$7 -> 93.153878 | S35: =P35*$C$10+Q35*$C$11+R35*$C$12 -> 4.0458999e+08 | T35: =(S35/S34)-1 -> 0.0039681066
B36: {=TRANSPOSE(C35:G35)} -> 1y | C36: =CORREL(TSIR!G831:G1080,TSIR!G831:G1080) -> 1 | D36: =CORREL(TSIR!G831:G1080,TSIR!H831:H1080) -> 0.90791142 | E36: =CORREL(TSIR!G831:G1080,TSIR!I831:I1080) -> 0.86685153 | F36: =CORREL(TSIR!G831:G1080,TSIR!J831:J1080) -> 0.8174392 | G36: =CORREL(TSIR!G831:G1080,TSIR!K831:K1080) -> 0.80107858 | J36: T19 | K36: =K35*((TSIR!B22/TSIR!B21)) -> 3.16 | L36: =L35*((TSIR!C22/TSIR!C21)) -> 3.1646154 | M36: =M35*((TSIR!D22/TSIR!D21)) -> 3.9811765 | N36: =N35*((TSIR!E22/TSIR!E21)) -> 4.337938 | O36: =O35*((TSIR!F22/TSIR!F21)) -> 4.5947368 | P36: =100/(1+(K36/100)) -> 96.936797 | Q36: =$F$6*((1-(1+M36/100)^(-$D$6))/(M36/100))+($F$6+100)/(1+$M$17/100)^$D$6 -> 107.87426 | R36: =$F$7*((1-(1+O36/100)^(-$D$7))/(O36/100))+($F$7+100)/(1+$O$17/100)^$D$7 -> 93.078739 | S36: =P36*$C$10+Q36*$C$11+R36*$C$12 -> 4.0437716e+08 | T36: =(S36/S35)-1 -> -0.00052602343
B37: 2y | C37: =CORREL(TSIR!H744:H993,TSIR!G744:G993) -> 0.90862351 | D37: =CORREL(TSIR!H831:H1080,TSIR!H831:H1080) -> 1 | E37: =CORREL(TSIR!H831:H1080,TSIR!I831:I1080) -> 0.94728722 | F37: =CORREL(TSIR!H831:H1080,TSIR!J831:J1080) -> 0.89139759 | G37: =CORREL(TSIR!H831:H1080,TSIR!K831:K1080) -> 0.909464 | J37: T20 | K37: =K36*((TSIR!B23/TSIR!B22)) -> 3.16 | L37: =L36*((TSIR!C23/TSIR!C22)) -> 3.1646154 | M37: =M36*((TSIR!D23/TSIR!D22)) -> 4.2023529 | N37: =N36*((TSIR!E23/TSIR!E22)) -> 4.4736 | O37: =O36*((TSIR!F23/TSIR!F22)) -> 4.6968421 | P37: =100/(1+(K37/100)) -> 96.936797 | Q37: =$F$6*((1-(1+M37/100)^(-$D$6))/(M37/100))+($F$6+100)/(1+$M$17/100)^$D$6 -> 107.81618 | R37: =$F$7*((1-(1+O37/100)^(-$D$7))/(O37/100))+($F$7+100)/(1+$O$17/100)^$D$7 -> 93.053917 | S37: =P37*$C$10+Q37*$C$11+R37*$C$12 -> 4.0436499e+08 | T37: =(S37/S36)-1 -> -3.0104251e-05
B38: 3y | C38: =CORREL(TSIR!I831:I1080,TSIR!G831:G1080) -> 0.86685153 | D38: =CORREL(TSIR!I831:I1080,TSIR!H831:H1080) -> 0.94728722 | E38: =CORREL(TSIR!B831:B1080,TSIR!B831:B1080) -> 1 | F38: =CORREL(TSIR!I831:I1080,TSIR!J831:J1080) -> 0.93224196 | G38: =CORREL(TSIR!I831:I1080,TSIR!K831:K1080) -> 0.95054192 | J38: T21 | K38: =K37*((TSIR!B24/TSIR!B23)) -> 2.765 | L38: =L37*((TSIR!C24/TSIR!C23)) -> 3.1646154 | M38: =M37*((TSIR!D24/TSIR!D23)) -> 3.9811765 | N38: =N37*((TSIR!E24/TSIR!E23)) -> 4.4057637 | O38: =O37*((TSIR!F24/TSIR!F23)) -> 4.6968421 | P38: =100/(1+(K38/100)) -> 97.309395 | Q38: =$F$6*((1-(1+M38/100)^(-$D$6))/(M38/100))+($F$6+100)/(1+$M$17/100)^$D$6 -> 107.87426 | R38: =$F$7*((1-(1+O38/100)^(-$D$7))/(O38/100))+($F$7+100)/(1+$O$17/100)^$D$7 -> 93.053917 | S38: =P38*$C$10+Q38*$C$11+R38*$C$12 -> 4.0502307e+08 | T38: =(S38/S37)-1 -> 0.001627443
B39: 4y | C39: =CORREL(TSIR!J831:J1080,TSIR!G831:G1080) -> 0.8174392 | D39: =CORREL(TSIR!J831:J1080,TSIR!H831:H1080) -> 0.89139759 | E39: =CORREL(TSIR!J831:J1080,TSIR!I831:I1080) -> 0.93224196 | F39: =CORREL(TSIR!J831:J1080,TSIR!J831:J1080) -> 1 | G39: =CORREL(TSIR!J831:J1080,TSIR!K831:K1080) -> 0.96271997 | J39: T22 | K39: =K38*((TSIR!B25/TSIR!B24)) -> 2.37 | L39: =L38*((TSIR!C25/TSIR!C24)) -> 2.5892308 | M39: =M38*((TSIR!D25/TSIR!D24)) -> 4.2023529 | N39: =N38*((TSIR!E25/TSIR!E24)) -> 4.5432257 | O39: =O38*((TSIR!F25/TSIR!F24)) -> 4.7989474 | P39: =100/(1+(K39/100)) -> 97.684869 | Q39: =$F$6*((1-(1+M39/100)^(-$D$6))/(M39/100))+($F$6+100)/(1+$M$17/100)^$D$6 -> 107.81618 | R39: =$F$7*((1-(1+O39/100)^(-$D$7))/(O39/100))+($F$7+100)/(1+$O$17/100)^$D$7 -> 93.029206 | S39: =P39*$C$10+Q39*$C$11+R39*$C$12 -> 4.0576229e+08 | T39: =(S39/S38)-1 -> 0.0018251236
B40: 5y | C40: =CORREL(TSIR!K831:K1080,TSIR!G831:G1080) -> 0.80107858 | D40: =CORREL(TSIR!K831:K1080,TSIR!H831:H1080) -> 0.909464 | E40: =CORREL(TSIR!K831:K1080,TSIR!I831:I1080) -> 0.95054192 | F40: =CORREL(TSIR!K831:K1080,TSIR!J831:J1080) -> 0.96271997 | G40: =CORREL(TSIR!K831:K1080,TSIR!K831:K1080) -> 1 | J40: T23 | K40: =K39*((TSIR!B26/TSIR!B25)) -> 2.765 | L40: =L39*((TSIR!C26/TSIR!C25)) -> 3.1646154 | M40: =M39*((TSIR!D26/TSIR!D25)) -> 4.4235294 | N40: =N39*((TSIR!E26/TSIR!E25)) -> 4.6783703 | O40: =O39*((TSIR!F26/TSIR!F25)) -> 4.9010526 | P40: =100/(1+(K40/100)) -> 97.309395 | Q40: =$F$6*((1-(1+M40/100)^(-$D$6))/(M40/100))+($F$6+100)/(1+$M$17/100)^$D$6 -> 107.75851 | R40: =$F$7*((1-(1+O40/100)^(-$D$7))/(O40/100))+($F$7+100)/(1+$O$17/100)^$D$7 -> 93.004605 | S40: =P40*$C$10+Q40*$C$11+R40*$C$12 -> 4.0499944e+08 | T40: =(S40/S39)-1 -> -0.0018800295
J41: T24 | K41: =K40*((TSIR!B27/TSIR!B26)) -> 2.765 | L41: =L40*((TSIR!C27/TSIR!C26)) -> 3.1646154 | M41: =M40*((TSIR!D27/TSIR!D26)) -> 4.2023529 | N41: =N40*((TSIR!E27/TSIR!E26)) -> 4.6083092 | O41: =O40*((TSIR!F27/TSIR!F26)) -> 4.9010526 | P41: =100/(1+(K41/100)) -> 97.309395 | Q41: =$F$6*((1-(1+M41/100)^(-$D$6))/(M41/100))+($F$6+100)/(1+$M$17/100)^$D$6 -> 107.81618 | R41: =$F$7*((1-(1+O41/100)^(-$D$7))/(O41/100))+($F$7+100)/(1+$O$17/100)^$D$7 -> 93.004605 | S41: =P41*$C$10+Q41*$C$11+R41*$C$12 -> 4.0491294e+08 | T41: =(S41/S40)-1 -> -0.00021359319
B42: VCV | C42: 1y | D42: 2y | E42: 3y | F42: 4y | G42: 5y | J42: T25 | K42: =K41*((TSIR!B28/TSIR!B27)) -> 2.765 | L42: =L41*((TSIR!C28/TSIR!C27)) -> 3.1646154 | M42: =M41*((TSIR!D28/TSIR!D27)) -> 4.2023529 | N42: =N41*((TSIR!E28/TSIR!E27)) -> 4.4719873 | O42: =O41*((TSIR!F28/TSIR!F27)) -> 4.6968421 | P42: =100/(1+(K42/100)) -> 97.309395 | Q42: =$F$6*((1-(1+M42/100)^(-$D$6))/(M42/100))+($F$6+100)/(1+$M$17/100)^$D$6 -> 107.81618 | R42: =$F$7*((1-(1+O42/100)^(-$D$7))/(O42/100))+($F$7+100)/(1+$O$17/100)^$D$7 -> 93.053917 | S42: =P42*$C$10+Q42*$C$11+R42*$C$12 -> 4.0511019e+08 | T42: =(S42/S41)-1 -> 0.00048713701
B43: {=TRANSPOSE(C42:G42)} -> 1y | C43: {=MMULT(MMULT(C36:G40,C29:G33),C29:G33)} -> 1.8532941e-07 | D43: 1.1817704e-06 | E43: 2.611174e-06 | F43: 2.8681702e-06 | G43: 6.8219797e-06 | J43: T26 | K43: =K42*((TSIR!B29/TSIR!B28)) -> 2.765 | L43: =L42*((TSIR!C29/TSIR!C28)) -> 3.1646154 | M43: =M42*((TSIR!D29/TSIR!D28)) -> 4.2023529 | N43: =N42*((TSIR!E29/TSIR!E28)) -> 4.475552 | O43: =O42*((TSIR!F29/TSIR!F28)) -> 4.6968421 | P43: =100/(1+(K43/100)) -> 97.309395 | Q43: =$F$6*((1-(1+M43/100)^(-$D$6))/(M43/100))+($F$6+100)/(1+$M$17/100)^$D$6 -> 107.81618 | R43: =$F$7*((1-(1+O43/100)^(-$D$7))/(O43/100))+($F$7+100)/(1+$O$17/100)^$D$7 -> 93.053917 | S43: =P43*$C$10+Q43*$C$11+R43*$C$12 -> 4.0511019e+08 | T43: =(S43/S42)-1 -> 0
B44: 2y | C44: 1.6839466e-07 | D44: 1.3016362e-06 | E44: 2.8534664e-06 | F44: 3.1276699e-06 | G44: 7.7449892e-06 | J44: T27 | K44: =K43*((TSIR!B30/TSIR!B29)) -> 2.37 | L44: =L43*((TSIR!C30/TSIR!C29)) -> 3.1646154 | M44: =M43*((TSIR!D30/TSIR!D29)) -> 4.4235294 | N44: =N43*((TSIR!E30/TSIR!E29)) -> 4.8177121 | O44: =O43*((TSIR!F30/TSIR!F29)) -> 5.1052632 | P44: =100/(1+(K44/100)) -> 97.684869 | Q44: =$F$6*((1-(1+M44/100)^(-$D$6))/(M44/100))+($F$6+100)/(1+$M$17/100)^$D$6 -> 107.75851 | R44: =$F$7*((1-(1+O44/100)^(-$D$7))/(O44/100))+($F$7+100)/(1+$O$17/100)^$D$7 -> 92.955732 | S44: =P44*$C$10+Q44*$C$11+R44*$C$12 -> 4.055549e+08 | T44: =(S44/S43)-1 -> 0.0010977526
B45: 3y | C45: 1.6065309e-07 | D45: 1.2330233e-06 | E45: 3.0122505e-06 | F45: 3.2709816e-06 | G45: 8.0948085e-06 | J45: T28 | K45: =K44*((TSIR!B31/TSIR!B30)) -> 3.16 | L45: =L44*((TSIR!C31/TSIR!C30)) -> 3.74 | M45: =M44*((TSIR!D31/TSIR!D30)) -> 5.0870588 | N45: =N44*((TSIR!E31/TSIR!E30)) -> 5.505812 | O45: =O44*((TSIR!F31/TSIR!F30)) -> 5.82 | P45: =100/(1+(K45/100)) -> 96.936797 | Q45: =$F$6*((1-(1+M45/100)^(-$D$6))/(M45/100))+($F$6+100)/(1+$M$17/100)^$D$6 -> 107.5879 | R45: =$F$7*((1-(1+O45/100)^(-$D$7))/(O45/100))+($F$7+100)/(1+$O$17/100)^$D$7 -> 92.788058 | S45: =P45*$C$10+Q45*$C$11+R45*$C$12 -> 4.0364397e+08 | T45: =(S45/S44)-1 -> -0.0047118737
B46: 4y | C46: 1.5149553e-07 | D46: 1.1602754e-06 | E46: 2.8081463e-06 | F46: 3.508726e-06 | G46: 8.1985167e-06 | J46: T29 | K46: =K45*((TSIR!B32/TSIR!B31)) -> 2.765 | L46: =L45*((TSIR!C32/TSIR!C31)) -> 3.1646154 | M46: =M45*((TSIR!D32/TSIR!D31)) -> 4.6447059 | N46: =N45*((TSIR!E32/TSIR!E31)) -> 5.3693371 | O46: =O45*((TSIR!F32/TSIR!F31)) -> 5.82 | P46: =100/(1+(K46/100)) -> 97.309395 | Q46: =$F$6*((1-(1+M46/100)^(-$D$6))/(M46/100))+($F$6+100)/(1+$M$17/100)^$D$6 -> 107.70124 | R46: =$F$7*((1-(1+O46/100)^(-$D$7))/(O46/100))+($F$7+100)/(1+$O$17/100)^$D$7 -> 92.788058 | S46: =P46*$C$10+Q46*$C$11+R46*$C$12 -> 4.0421916e+08 | T46: =(S46/S45)-1 -> 0.0014249784
B47: 5y | C47: 1.4846342e-07 | D47: 1.1837913e-06 | E47: 2.8632704e-06 | F47: 3.3779206e-06 | G47: 8.5159932e-06 | J47: T30 | K47: =K46*((TSIR!B33/TSIR!B32)) -> 2.37 | L47: =L46*((TSIR!C33/TSIR!C32)) -> 3.1646154 | M47: =M46*((TSIR!D33/TSIR!D32)) -> 4.6447059 | N47: =N46*((TSIR!E33/TSIR!E32)) -> 5.2950655 | O47: =O46*((TSIR!F33/TSIR!F32)) -> 5.7178947 | P47: =100/(1+(K47/100)) -> 97.684869 | Q47: =$F$6*((1-(1+M47/100)^(-$D$6))/(M47/100))+($F$6+100)/(1+$M$17/100)^$D$6 -> 107.70124 | R47: =$F$7*((1-(1+O47/100)^(-$D$7))/(O47/100))+($F$7+100)/(1+$O$17/100)^$D$7 -> 92.811694 | S47: =P47*$C$10+Q47*$C$11+R47*$C$12 -> 4.0506465e+08 | T47: =(S47/S46)-1 -> 0.0020916649
J48: T31 | K48: =K47*((TSIR!B34/TSIR!B33)) -> 2.765 | L48: =L47*((TSIR!C34/TSIR!C33)) -> 3.1646154 | M48: =M47*((TSIR!D34/TSIR!D33)) -> 4.8658824 | N48: =N47*((TSIR!E34/TSIR!E33)) -> 5.5736492 | O48: =O47*((TSIR!F34/TSIR!F33)) -> 6.0242105 | P48: =100/(1+(K48/100)) -> 97.309395 | Q48: =$F$6*((1-(1+M48/100)^(-$D$6))/(M48/100))+($F$6+100)/(1+$M$17/100)^$D$6 -> 107.64438 | R48: =$F$7*((1-(1+O48/100)^(-$D$7))/(O48/100))+($F$7+100)/(1+$O$17/100)^$D$7 -> 92.741098 | S48: =P48*$C$10+Q48*$C$11+R48*$C$12 -> 4.0411662e+08 | T48: =(S48/S47)-1 -> -0.0023404403
J49: T32 | K49: =K48*((TSIR!B35/TSIR!B34)) -> 2.37 | L49: =L48*((TSIR!C35/TSIR!C34)) -> 3.1646154 | M49: =M48*((TSIR!D35/TSIR!D34)) -> 4.8658824 | N49: =N48*((TSIR!E35/TSIR!E34)) -> 5.7088576 | O49: =O48*((TSIR!F35/TSIR!F34)) -> 6.2284211 | P49: =100/(1+(K49/100)) -> 97.684869 | Q49: =$F$6*((1-(1+M49/100)^(-$D$6))/(M49/100))+($F$6+100)/(1+$M$17/100)^$D$6 -> 107.64438 | R49: =$F$7*((1-(1+O49/100)^(-$D$7))/(O49/100))+($F$7+100)/(1+$O$17/100)^$D$7 -> 92.694549 | S49: =P49*$C$10+Q49*$C$11+R49*$C$12 -> 4.0468137e+08 | T49: =(S49/S48)-1 -> 0.0013975007
J50: T33 | K50: =K49*((TSIR!B36/TSIR!B35)) -> 3.16 | L50: =L49*((TSIR!C36/TSIR!C35)) -> 3.1646154 | M50: =M49*((TSIR!D36/TSIR!D35)) -> 4.8658824 | N50: =N49*((TSIR!E36/TSIR!E35)) -> 5.5757488 | O50: =O49*((TSIR!F36/TSIR!F35)) -> 6.0242105 | P50: =100/(1+(K50/100)) -> 96.936797 | Q50: =$F$6*((1-(1+M50/100)^(-$D$6))/(M50/100))+($F$6+100)/(1+$M$17/100)^$D$6 -> 107.64438 | R50: =$F$7*((1-(1+O50/100)^(-$D$7))/(O50/100))+($F$7+100)/(1+$O$17/100)^$D$7 -> 92.741098 | S50: =P50*$C$10+Q50*$C$11+R50*$C$12 -> 4.0337142e+08 | T50: =(S50/S49)-1 -> -0.0032369893
J51: T34 | K51: =K50*((TSIR!B37/TSIR!B36)) -> 3.16 | L51: =L50*((TSIR!C37/TSIR!C36)) -> 3.4523077 | M51: =M50*((TSIR!D37/TSIR!D36)) -> 5.3082353 | N51: =N50*((TSIR!E37/TSIR!E36)) -> 5.9161933 | O51: =O50*((TSIR!F37/TSIR!F36)) -> 6.3305263 | P51: =100/(1+(K51/100)) -> 96.936797 | Q51: =$F$6*((1-(1+M51/100)^(-$D$6))/(M51/100))+($F$6+100)/(1+$M$17/100)^$D$6 -> 107.53182 | R51: =$F$7*((1-(1+O51/100)^(-$D$7))/(O51/100))+($F$7+100)/(1+$O$17/100)^$D$7 -> 92.671428 | S51: =P51*$C$10+Q51*$C$11+R51*$C$12 -> 4.0326158e+08 | T51: =(S51/S50)-1 -> -0.00027232068
J52: T35 | K52: =K51*((TSIR!B38/TSIR!B37)) -> 3.555 | L52: =L51*((TSIR!C38/TSIR!C37)) -> 4.8907692 | M52: =M51*((TSIR!D38/TSIR!D37)) -> 7.52 | N52: =N51*((TSIR!E38/TSIR!E37)) -> 7.9096412 | O52: =O51*((TSIR!F38/TSIR!F37)) -> 8.2705263 | P52: =100/(1+(K52/100)) -> 96.567042 | Q52: =$F$6*((1-(1+M52/100)^(-$D$6))/(M52/100))+($F$6+100)/(1+$M$17/100)^$D$6 -> 106.99175 | R52: =$F$7*((1-(1+O52/100)^(-$D$7))/(O52/100))+($F$7+100)/(1+$O$17/100)^$D$7 -> 92.250722 | S52: =P52*$C$10+Q52*$C$11+R52*$C$12 -> 4.0164934e+08 | T52: =(S52/S51)-1 -> -0.0039979834
J53: T36 | K53: =K52*((TSIR!B39/TSIR!B38)) -> 3.16 | L53: =L52*((TSIR!C39/TSIR!C38)) -> 4.0276923 | M53: =M52*((TSIR!D39/TSIR!D38)) -> 6.6352941 | N53: =N52*((TSIR!E39/TSIR!E38)) -> 7.2219024 | O53: =O52*((TSIR!F39/TSIR!F38)) -> 7.6578947 | P53: =100/(1+(K53/100)) -> 96.936797 | Q53: =$F$6*((1-(1+M53/100)^(-$D$6))/(M53/100))+($F$6+100)/(1+$M$17/100)^$D$6 -> 107.20335 | R53: =$F$7*((1-(1+O53/100)^(-$D$7))/(O53/100))+($F$7+100)/(1+$O$17/100)^$D$7 -> 92.379859 | S53: =P53*$C$10+Q53*$C$11+R53*$C$12 -> 4.02588e+08 | T53: =(S53/S52)-1 -> 0.0023370152
J54: T37 | K54: =K53*((TSIR!B40/TSIR!B39)) -> 3.16 | L54: =L53*((TSIR!C40/TSIR!C39)) -> 3.74 | M54: =M53*((TSIR!D40/TSIR!D39)) -> 5.9717647 | N54: =N53*((TSIR!E40/TSIR!E39)) -> 6.7412342 | O54: =O53*((TSIR!F40/TSIR!F39)) -> 7.2494737 | P54: =100/(1+(K54/100)) -> 96.936797 | Q54: =$F$6*((1-(1+M54/100)^(-$D$6))/(M54/100))+($F$6+100)/(1+$M$17/100)^$D$6 -> 107.36589 | R54: =$F$7*((1-(1+O54/100)^(-$D$7))/(O54/100))+($F$7+100)/(1+$O$17/100)^$D$7 -> 92.467824 | S54: =P54*$C$10+Q54*$C$11+R54*$C$12 -> 4.0269606e+08 | T54: =(S54/S53)-1 -> 0.00026840159
J55: T38 | K55: =K54*((TSIR!B41/TSIR!B40)) -> 3.16 | L55: =L54*((TSIR!C41/TSIR!C40)) -> 3.74 | M55: =M54*((TSIR!D41/TSIR!D40)) -> 5.7505882 | N55: =N54*((TSIR!E41/TSIR!E40)) -> 6.3942485 | O55: =O54*((TSIR!F41/TSIR!F40)) -> 6.8410526 | P55: =100/(1+(K55/100)) -> 96.936797 | Q55: =$F$6*((1-(1+M55/100)^(-$D$6))/(M55/100))+($F$6+100)/(1+$M$17/100)^$D$6 -> 107.42082 | R55: =$F$7*((1-(1+O55/100)^(-$D$7))/(O55/100))+($F$7+100)/(1+$O$17/100)^$D$7 -> 92.557329 | S55: =P55*$C$10+Q55*$C$11+R55*$C$12 -> 4.0297169e+08 | T55: =(S55/S54)-1 -> 0.00068445092
J56: T39 | K56: =K55*((TSIR!B42/TSIR!B41)) -> 3.16 | L56: =L55*((TSIR!C42/TSIR!C41)) -> 4.0276923 | M56: =M55*((TSIR!D42/TSIR!D41)) -> 6.4141176 | N56: =N55*((TSIR!E42/TSIR!E41)) -> 7.0138908 | O56: =O55*((TSIR!F42/TSIR!F41)) -> 7.4536842 | P56: =100/(1+(K56/100)) -> 96.936797 | Q56: =$F$6*((1-(1+M56/100)^(-$D$6))/(M56/100))+($F$6+100)/(1+$M$17/100)^$D$6 -> 107.25716 | R56: =$F$7*((1-(1+O56/100)^(-$D$7))/(O56/100))+($F$7+100)/(1+$O$17/100)^$D$7 -> 92.423651 | S56: =P56*$C$10+Q56*$C$11+R56*$C$12 -> 4.0268246e+08 | T56: =(S56/S55)-1 -> -0.00071772508
J57: T40 | K57: =K56*((TSIR!B43/TSIR!B42)) -> 3.16 | L57: =L56*((TSIR!C43/TSIR!C42)) -> 4.0276923 | M57: =M56*((TSIR!D43/TSIR!D42)) -> 7.0776471 | N57: =N56*((TSIR!E43/TSIR!E42)) -> 7.4981938 | O57: =O56*((TSIR!F43/TSIR!F42)) -> 7.8621053 | P57: =100/(1+(K57/100)) -> 96.936797 | Q57: =$F$6*((1-(1+M57/100)^(-$D$6))/(M57/100))+($F$6+100)/(1+$M$17/100)^$D$6 -> 107.09683 | R57: =$F$7*((1-(1+O57/100)^(-$D$7))/(O57/100))+($F$7+100)/(1+$O$17/100)^$D$7 -> 92.336443 | S57: =P57*$C$10+Q57*$C$11+R57*$C$12 -> 4.0257412e+08 | T57: =(S57/S56)-1 -> -0.00026905652
J58: T41 | K58: =K57*((TSIR!B44/TSIR!B43)) -> 3.16 | L58: =L57*((TSIR!C44/TSIR!C43)) -> 4.0276923 | M58: =M57*((TSIR!D44/TSIR!D43)) -> 7.0776471 | N58: =N57*((TSIR!E44/TSIR!E43)) -> 7.6379144 | O58: =O57*((TSIR!F44/TSIR!F43)) -> 8.0663158 | P58: =100/(1+(K58/100)) -> 96.936797 | Q58: =$F$6*((1-(1+M58/100)^(-$D$6))/(M58/100))+($F$6+100)/(1+$M$17/100)^$D$6 -> 107.09683 | R58: =$F$7*((1-(1+O58/100)^(-$D$7))/(O58/100))+($F$7+100)/(1+$O$17/100)^$D$7 -> 92.293398 | S58: =P58*$C$10+Q58*$C$11+R58*$C$12 -> 4.0240194e+08 | T58: =(S58/S57)-1 -> -0.00042768985
J59: T42 | K59: =K58*((TSIR!B45/TSIR!B44)) -> 3.555 | L59: =L58*((TSIR!C45/TSIR!C44)) -> 4.8907692 | M59: =M58*((TSIR!D45/TSIR!D44)) -> 7.52 | N59: =N58*((TSIR!E45/TSIR!E44)) -> 8.2539099 | O59: =O58*((TSIR!F45/TSIR!F44)) -> 8.7810526 | P59: =100/(1+(K59/100)) -> 96.567042 | Q59: =$F$6*((1-(1+M59/100)^(-$D$6))/(M59/100))+($F$6+100)/(1+$M$17/100)^$D$6 -> 106.99175 | R59: =$F$7*((1-(1+O59/100)^(-$D$7))/(O59/100))+($F$7+100)/(1+$O$17/100)^$D$7 -> 92.145614 | S59: =P59*$C$10+Q59*$C$11+R59*$C$12 -> 4.0122891e+08 | T59: =(S59/S58)-1 -> -0.0029150661
... J267: T250 | K267: =K266*((TSIR!B253/TSIR!B252)) -> 15.8 | L267: =L266*((TSIR!C253/TSIR!C252)) -> 22.44 | M267: =M266*((TSIR!D253/TSIR!D252)) -> 23.002353 | N267: =N266*((TSIR!E253/TSIR!E252)) -> 16.57083 | O267: =O266*((TSIR!F253/TSIR!F252)) -> 13.988421 | P267: =100/(1+(K267/100)) -> 86.355786 | Q267: =$F$6*((1-(1+M267/100)^(-$D$6))/(M267/100))+($F$6+100)/(1+$M$17/100)^$D$6 -> 104.05036 | R267: =$F$7*((1-(1+O267/100)^(-$D$7))/(O267/100))+($F$7+100)/(1+$O$17/100)^$D$7 -> 91.189989 | S267: =P267*$C$10+Q267*$C$11+R267*$C$12 -> 3.8139599e+08 | T267: =(S267/S266)-1 -> -0.0025849402

Sheet Total Fund Risk
B2: TOTAL FUND RISK | I2: 1
I3: 1st percentile Return : | J3: =_xlfn.PERCENTILE.INC(F19:F268,0.01) -> -0.034943796
I4: VaR(99%,1) : | J4: =ABS(J3)*E18 -> 15090501
B5: Insights | I5: Mean Below VaR : | J5: =AVERAGEIF(F19:F268,"<-0.0394") -> -0.05874482
B6: The VaR(99%,1) estimates a potential one-day loss of CHF 15–17 million with 99% confidence, | I6: ES(99%,1) : | J6: =ABS(J5*E18) -> 25368989
B7: while ES(99%,1) shows that if losses exceed VaR, they average CHF 23–25 million.
B8: This reflects a left-skewed distribution with considerable tail risk, | I8: 2
B9: which should be closely monitored under stressed conditions | I9: 1st percentile Return : | J9: =_xlfn.PERCENTILE.INC(K19:K268,0.01) -> -0.043851558
I10: VaR(99%,1) : | J10: =ABS(J9)*J18 -> 16835500
I11: Mean Below VaR : | J11: =AVERAGEIF(K19:K268,"<-0.04385") -> -0.059415977
I12: ES(99%,1) : | J12: =ABS(J11)*J18 -> 22810995
B17: date | C17: π_Options | D17: π_FI (USD) | E17: π (Mixed) | F17: R_π (Mixed) | H17: CHF/USD | I17: π_FI | J17: π | K17: R_π (CHF) | O17: Total VaR (CHF)
B18: 45772 | C18: 28226585 | D18: 4.0362406e+08 | E18: =C18+D18 -> 4.3185065e+08 | F18: 0 | H18: 1.134752 | I18: =D18/H18 -> 3.5569363e+08 | J18: =C18+I18 -> 3.8392022e+08 | K18: 0 | O18: =SQRT(15090501^2 + (2276909 * 1.105)^2 + 2 * 0 * 15090501 * (2276909 * 1.105)) -> 15298804
B19: T1 | C19: 23228208 | D19: 3.9817716e+08 | E19: =C19+D19 -> 4.2140537e+08 | F19: =(E19/E18)-1 -> -0.024187235 | H19: 1.129306 | I19: =D19/H19 -> 3.5258572e+08 | J19: =C19+I19 -> 3.7581392e+08 | K19: =(J19/J18)-1 -> -0.021114526
B20: T2 | C20: 28113757 | D20: 4.0242096e+08 | E20: =C20+D20 -> 4.3053472e+08 | F20: =(E20/E19)-1 -> 0.021664049 | H20: 1.130007 | I20: =D20/H20 -> 3.5612254e+08 | J20: =C20+I20 -> 3.842363e+08 | K20: =(J20/J19)-1 -> 0.022411017
B21: T3 | C21: 26885452 | D21: 4.0302292e+08 | E21: =C21+D21 -> 4.2990837e+08 | F21: =(E21/E20)-1 -> -0.0014548204 | H21: 1.132824 | I21: =D21/H21 -> 3.5576834e+08 | J21: =C21+I21 -> 3.8265379e+08 | K21: =(J21/J20)-1 -> -0.0041185645 | M21: Key Insights
B22: T4 | C22: 26396977 | D22: 4.0275656e+08 | E22: =C22+D22 -> 4.2915353e+08 | F22: =(E22/E21)-1 -> -0.0017558052 | H22: 1.13617 | I22: =D22/H22 -> 3.5448617e+08 | J22: =C22+I22 -> 3.8088315e+08 | K22: =(J22/J21)-1 -> -0.0046272724 | M22: Historical Simulation captured tail-risk more effectively than the Delta-Normal framework Fixed income risk remained sensitive to yield curve movements Portfolio aggregation reduced overall risk exposure due to diversification effects
B23: T5 | C23: 29447768 | D23: 4.0211293e+08 | E23: =C23+D23 -> 4.315607e+08 | F23: =(E23/E22)-1 -> 0.0056091013 | H23: 1.134559 | I23: =D23/H23 -> 3.5442223e+08 | J23: =C23+I23 -> 3.8387e+08 | K23: =(J23/J22)-1 -> 0.0078418986
B24: T6 | C24: 25762012 | D24: 4.0150087e+08 | E24: =C24+D24 -> 4.2726289e+08 | F24: =(E24/E23)-1 -> -0.0099587694 | H24: 1.13798 | I24: =D24/H24 -> 3.5281892e+08 | J24: =C24+I24 -> 3.7858093e+08 | K24: =(J24/J23)-1 -> -0.013778277
B25: T7 | C25: 30300056 | D25: 4.0293879e+08 | E25: =C25+D25 -> 4.3323885e+08 | F25: =(E25/E24)-1 -> 0.013986623 | H25: 1.128605 | I25: =D25/H25 -> 3.5702375e+08 | J25: =C25+I25 -> 3.8732381e+08 | K25: =(J25/J24)-1 -> 0.023093819
B26: T8 | C26: 29245031 | D26: 4.0297809e+08 | E26: =C26+D26 -> 4.3222312e+08 | F26: =(E26/E25)-1 -> -0.002344493 | H26: 1.125302 | I26: =D26/H26 -> 3.5810662e+08 | J26: =C26+I26 -> 3.8735165e+08 | K26: =(J26/J25)-1 -> 7.1875201e-05
B27: T9 | C27: 28849058 | D27: 4.0316328e+08 | E27: =C27+D27 -> 4.3201234e+08 | F27: =(E27/E26)-1 -> -0.00048767399 | H27: 1.123028 | I27: =D27/H27 -> 3.5899664e+08 | J27: =C27+I27 -> 3.878457e+08 | K27: =(J27/J26)-1 -> 0.0012754622
B28: T10 | C28: 25401890 | D28: 4.0299088e+08 | E28: =C28+D28 -> 4.2839277e+08 | F28: =(E28/E27)-1 -> -0.0083784038 | H28: 1.113152 | I28: =D28/H28 -> 3.6202682e+08 | J28: =C28+I28 -> 3.8742871e+08 | K28: =(J28/J27)-1 -> -0.0010751525
B29: T11 | C29: 31608047 | D29: 4.0299088e+08 | E29: =C29+D29 -> 4.3459892e+08 | F29: =(E29/E28)-1 -> 0.014487073 | H29: 1.10834 | I29: =D29/H29 -> 3.635986e+08 | J29: =C29+I29 -> 3.9520665e+08 | K29: =(J29/J28)-1 -> 0.020075804
B30: T12 | C30: 28908294 | D30: 4.0309061e+08 | E30: =C30+D30 -> 4.3199891e+08 | F30: =(E30/E29)-1 -> -0.0059825692 | H30: 1.111914 | I30: =D30/H30 -> 3.6251959e+08 | J30: =C30+I30 -> 3.9142789e+08 | K30: =(J30/J29)-1 -> -0.0095614869
B31: T13 | C31: 33420611 | D31: 4.0311659e+08 | E31: =C31+D31 -> 4.365372e+08 | F31: =(E31/E30)-1 -> 0.01050533 | H31: 1.118944 | I31: =D31/H31 -> 3.602652e+08 | J31: =C31+I31 -> 3.9368581e+08 | K31: =(J31/J30)-1 -> 0.0057684315
B32: T14 | C32: 30399832 | D32: 4.0393821e+08 | E32: =C32+D32 -> 4.3433804e+08 | F32: =(E32/E31)-1 -> -0.0050377326 | H32: 1.119132 | I32: =D32/H32 -> 3.6093884e+08 | J32: =C32+I32 -> 3.9133867e+08 | K32: =(J32/J31)-1 -> -0.0059619613
B33: T15 | C33: 30758333 | D33: 4.040393e+08 | E33: =C33+D33 -> 4.3479763e+08 | F33: =(E33/E32)-1 -> 0.0010581423 | H33: 1.114765 | I33: =D33/H33 -> 3.6244347e+08 | J33: =C33+I33 -> 3.9320181e+08 | K33: =(J33/J32)-1 -> 0.0047609208
B34: T16 | C34: 28575590 | D34: 4.0467772e+08 | E34: =C34+D34 -> 4.3325331e+08 | F34: =(E34/E33)-1 -> -0.0035518173 | H34: 1.111667 | I34: =D34/H34 -> 3.6402782e+08 | J34: =C34+I34 -> 3.9260341e+08 | K34: =(J34/J33)-1 -> -0.0015218435
... B268: T250 | C268: 37845899 | D268: 3.8139599e+08 | E268: =C268+D268 -> 4.1924189e+08 | F268: =(E268/E267)-1 -> 0.03378462 | H268: 1.105156 | I268: =D268/H268 -> 3.4510602e+08 | J268: =C268+I268 -> 3.8295192e+08 | K268: =(J268/J267)-1 -> 0.035866382
